Workbook

Sheet Readme
H5: FP&A / Strategic Finance Platform
D6: Template SaaS Financial Model
D7: Get started! This B2B SaaS financial model template helps you forecast your company's future performance using a connected driver-based model. The template is intended as a starting point for SaaS companies to model revenues and project their financial performance. We understand no two businesses are the same, and you can modify it as needed to suit the needs of your business. The key components of this SaaS financial model include: • Assumptions • Actuals sheet (to record your historical data) • ARR Summary • Customer Summary • Average Contract Value Summary • Churn Metrics • SaaS Metrics • Income Statement (P&L) • Customer Control • Dashboard
D10: Cell value type | F10: Description
D12: Input (Actuals or Assumptions) | F12: Manually input your actuals data or assumption values in these cells shaded in light yellow. Note: These cells have been pre-populated with sample data
D13: Formula | F13: These cells are automatically calculated using a formula. You can edit the formula to suit your needs

Sheet Key Assumptions
A2: Assumptions SaaS Financial Model
C4: Notes
C5: 1. Enter the start and end dates for the period you have historical data. Feel free to enter the data for whatever time period is available
C6: 2. The forecast period starts 1-day post the end of the historical period specified. The forecast period is set to 36 months
C7: 3. Enter your assumptions for pipeline, expansion and income statement metrics
C8: 4. Rows 19-22 (hidden) contain flags for indicating historical or forecast columns and the year column (for annual roll-ups). Toggle these to "1" for rolling your forecasts over time. This applies to all sheets.
C12: Model Timeline | G12: Format type | I12: =IF(I20=1,"Actual","Forecast") -> Actual | J12: =IF(J20=1,"Actual","Forecast") -> Actual | K12: =IF(K20=1,"Actual","Forecast") -> Forecast | L12: =IF(L20=1,"Actual","Forecast") -> Forecast | M12: =IF(M20=1,"Actual","Forecast") -> Forecast | O12: =IF(O20=1,"Actual","Forecast") -> Actual | P12: =IF(P20=1,"Actual","Forecast") -> Actual | Q12: =IF(Q20=1,"Actual","Forecast") -> Actual | R12: =IF(R20=1,"Actual","Forecast") -> Actual | S12: =IF(S20=1,"Actual","Forecast") -> Actual | T12: =IF(T20=1,"Actual","Forecast") -> Actual | U12: =IF(U20=1,"Actual","Forecast") -> Actual | V12: =IF(V20=1,"Actual","Forecast") -> Actual | ... BV12: =IF(BV20=1,"Actual","Forecast") -> Forecast
C13: Start of Historical Period | D13: 44562 | H13: Date | I13: =I14 -> 44562 | J13: =J14 -> 44927 | K13: =K14 -> 45292 | L13: =L14 -> 45658 | M13: =M14 -> 46023 | O13: =O14 -> 44562 | P13: =P14 -> 44593 | Q13: =Q14 -> 44621 | R13: =R14 -> 44652 | S13: =S14 -> 44682 | T13: =T14 -> 44713 | U13: =U14 -> 44743 | V13: =V14 -> 44774 | ... BV13: =BV14 -> 46357
C14: End of Historical Period | D14: 45107 | H14: Start of Period | I14: ='Key Assumptions'!D13 -> 44562 | J14: =I15+1 -> 44927 | K14: =J15+1 -> 45292 | L14: =K15+1 -> 45658 | M14: =L15+1 -> 46023 | O14: ='Key Assumptions'!D13 -> 44562 | P14: =O15+1 -> 44593 | Q14: =P15+1 -> 44621 | R14: =Q15+1 -> 44652 | S14: =R15+1 -> 44682 | T14: =S15+1 -> 44713 | U14: =T15+1 -> 44743 | V14: =U15+1 -> 44774 | W14: =V15+1 -> 44805 | ... BV14: =BU15+1 -> 46357
C15: Start of Forecast Period | D15: =D14+1 -> 45108 | H15: End of Period | I15: =EOMONTH(I14,11) -> 44926 | J15: =EOMONTH(J14,11) -> 45291 | K15: =EOMONTH(K14,11) -> 45657 | L15: =EOMONTH(L14,11) -> 46022 | M15: =EOMONTH(M14,11) -> 46387 | O15: =EOMONTH(O14,0) -> 44592 | P15: =EOMONTH(P14,0) -> 44620 | Q15: =EOMONTH(Q14,0) -> 44651 | R15: =EOMONTH(R14,0) -> 44681 | S15: =EOMONTH(S14,0) -> 44712 | T15: =EOMONTH(T14,0) -> 44742 | U15: =EOMONTH(U14,0) -> 44773 | V15: =EOMONTH(V14,0) -> 44804 | ... BV15: =EOMONTH(BV14,0) -> 46387
C16: End of Forecast Period | D16: =EOMONTH(D13,59) -> 46387 | H16: Timeline | I16: =IF(I15-I14>35,"Annual","Monthly") -> Annual | J16: =IF(J15-J14>35,"Annual","Monthly") -> Annual | K16: =IF(K15-K14>35,"Annual","Monthly") -> Annual | L16: =IF(L15-L14>35,"Annual","Monthly") -> Annual | M16: =IF(M15-M14>35,"Annual","Monthly") -> Annual | O16: =IF(O15-O14>35,"Annual","Monthly") -> Monthly | P16: =IF(P15-P14>35,"Annual","Monthly") -> Monthly | Q16: =IF(Q15-Q14>35,"Annual","Monthly") -> Monthly | R16: =IF(R15-R14>35,"Annual","Monthly") -> Monthly | S16: =IF(S15-S14>35,"Annual","Monthly") -> Monthly | T16: =IF(T15-T14>35,"Annual","Monthly") -> Monthly | U16: =IF(U15-U14>35,"Annual","Monthly") -> Monthly | V16: =IF(V15-V14>35,"Annual","Monthly") -> Monthly | ... BV16: =IF(BV15-BV14>35,"Annual","Monthly") -> Monthly
H17: Year | I17: =YEAR(I14) -> 2022 | J17: =YEAR(J14) -> 2023 | K17: =YEAR(K14) -> 2024 | L17: =YEAR(L14) -> 2025 | M17: =YEAR(M14) -> 2026 | O17: =YEAR(O14) -> 2022 | P17: =YEAR(P14) -> 2022 | Q17: =YEAR(Q14) -> 2022 | R17: =YEAR(R14) -> 2022 | S17: =YEAR(S14) -> 2022 | T17: =YEAR(T14) -> 2022 | U17: =YEAR(U14) -> 2022 | V17: =YEAR(V14) -> 2022 | ... BV17: =YEAR(BV14) -> 2026
H19: Flag
H20: Historical Flag | I20: =IF(AND(I14>='Key Assumptions'!$D$13,I14<'Key Assumptions'!$D$14),1,0) -> 1 | J20: =IF(AND(J14>='Key Assumptions'!$D$13,J14<'Key Assumptions'!$D$14),1,0) -> 1 | K20: =IF(AND(K14>='Key Assumptions'!$D$13,K14<'Key Assumptions'!$D$14),1,0) -> 0 | L20: =IF(AND(L14>='Key Assumptions'!$D$13,L14<'Key Assumptions'!$D$14),1,0) -> 0 | M20: =IF(AND(M14>='Key Assumptions'!$D$13,M14<'Key Assumptions'!$D$14),1,0) -> 0 | O20: =IF(AND(O14>='Key Assumptions'!$D$13,O14<'Key Assumptions'!$D$14),1,0) -> 1 | P20: =IF(AND(P14>='Key Assumptions'!$D$13,P14<'Key Assumptions'!$D$14),1,0) -> 1 | Q20: =IF(AND(Q14>='Key Assumptions'!$D$13,Q14<'Key Assumptions'!$D$14),1,0) -> 1 | R20: =IF(AND(R14>='Key Assumptions'!$D$13,R14<'Key Assumptions'!$D$14),1,0) -> 1 | S20: =IF(AND(S14>='Key Assumptions'!$D$13,S14<'Key Assumptions'!$D$14),1,0) -> 1 | T20: =IF(AND(T14>='Key Assumptions'!$D$13,T14<'Key Assumptions'!$D$14),1,0) -> 1 | U20: =IF(AND(U14>='Key Assumptions'!$D$13,U14<'Key Assumptions'!$D$14),1,0) -> 1 | V20: =IF(AND(V14>='Key Assumptions'!$D$13,V14<'Key Assumptions'!$D$14),1,0) -> 1 | ... BV20: =IF(AND(BV14>='Key Assumptions'!$D$13,BV14<'Key Assumptions'!$D$14),1,0) -> 0
H21: Forecast Flag | I21: =IF(AND(I14>='Key Assumptions'!$D$15,I14<'Key Assumptions'!$D$16),1,0) -> 0 | J21: =IF(AND(J14>='Key Assumptions'!$D$15,J14<'Key Assumptions'!$D$16),1,0) -> 0 | K21: =IF(AND(K14>='Key Assumptions'!$D$15,K14<'Key Assumptions'!$D$16),1,0) -> 1 | L21: =IF(AND(L14>='Key Assumptions'!$D$15,L14<'Key Assumptions'!$D$16),1,0) -> 1 | M21: =IF(AND(M14>='Key Assumptions'!$D$15,M14<'Key Assumptions'!$D$16),1,0) -> 1 | O21: =IF(AND(O14>='Key Assumptions'!$D$15,O14<'Key Assumptions'!$D$16),1,0) -> 0 | P21: =IF(AND(P14>='Key Assumptions'!$D$15,P14<'Key Assumptions'!$D$16),1,0) -> 0 | Q21: =IF(AND(Q14>='Key Assumptions'!$D$15,Q14<'Key Assumptions'!$D$16),1,0) -> 0 | R21: =IF(AND(R14>='Key Assumptions'!$D$15,R14<'Key Assumptions'!$D$16),1,0) -> 0 | S21: =IF(AND(S14>='Key Assumptions'!$D$15,S14<'Key Assumptions'!$D$16),1,0) -> 0 | T21: =IF(AND(T14>='Key Assumptions'!$D$15,T14<'Key Assumptions'!$D$16),1,0) -> 0 | U21: =IF(AND(U14>='Key Assumptions'!$D$15,U14<'Key Assumptions'!$D$16),1,0) -> 0 | V21: =IF(AND(V14>='Key Assumptions'!$D$15,V14<'Key Assumptions'!$D$16),1,0) -> 0 | ... BV21: =IF(AND(BV14>='Key Assumptions'!$D$15,BV14<'Key Assumptions'!$D$16),1,0) -> 1
H22: Year Flag | I22: =COUNTA($I$14:I14) -> 1 | J22: =COUNTA($I$14:J14) -> 2 | K22: =COUNTA($I$14:K14) -> 3 | L22: =COUNTA($I$14:L14) -> 4 | M22: =COUNTA($I$14:M14) -> 5 | O22: =INDEX($I$22:$M$22,MATCH(YEAR(O$14),$I$17:$M$17,0)) -> 1 | P22: =INDEX($I$22:$M$22,MATCH(YEAR(P$14),$I$17:$M$17,0)) -> 1 | Q22: =INDEX($I$22:$M$22,MATCH(YEAR(Q$14),$I$17:$M$17,0)) -> 1 | R22: =INDEX($I$22:$M$22,MATCH(YEAR(R$14),$I$17:$M$17,0)) -> 1 | S22: =INDEX($I$22:$M$22,MATCH(YEAR(S$14),$I$17:$M$17,0)) -> 1 | T22: =INDEX($I$22:$M$22,MATCH(YEAR(T$14),$I$17:$M$17,0)) -> 1 | U22: =INDEX($I$22:$M$22,MATCH(YEAR(U$14),$I$17:$M$17,0)) -> 1 | V22: =INDEX($I$22:$M$22,MATCH(YEAR(V$14),$I$17:$M$17,0)) -> 1 | ... BV22: =INDEX($I$22:$M$22,MATCH(YEAR(BV$14),$I$17:$M$17,0)) -> 5
C25: Pipeline assumptions
C26: Leads per month | G26: # | I26: =SUMIFS($O26:$BV26,$O$22:$BV$22,I$22) -> 6000 | J26: =SUMIFS($O26:$BV26,$O$22:$BV$22,J$22) -> 6000 | K26: =SUMIFS($O26:$BV26,$O$22:$BV$22,K$22) -> 6000 | L26: =SUMIFS($O26:$BV26,$O$22:$BV$22,L$22) -> 6000 | M26: =SUMIFS($O26:$BV26,$O$22:$BV$22,M$22) -> 6000 | O26: 500 | P26: 500 | Q26: 500 | R26: 500 | S26: 500 | T26: 500 | U26: 500 | V26: 500 | W26: 500 | X26: 500 | Y26: 500 | Z26: 500 | AA26: 500 | AB26: 500 | AC26: 500 | AD26: 500 | AE26: 500 | AF26: 500 | AG26: 500 | AH26: 500 | AI26: 500 | AJ26: 500 | AK26: 500 | AL26: 500 | AM26: 500 | AN26: 500 | AO26: 500 | AP26: 500 | AQ26: 500 | AR26: 500 | AS26: 500 | AT26: 500 | AU26: 500 | AV26: 500 | AW26: 500 | AX26: 500 | AY26: 500 | AZ26: 500 | BA26: 500 | BB26: 500 | BC26: 500 | BD26: 500 | BE26: 500 | BF26: 500 | BG26: 500 | BH26: 500 | BI26: 500 | BJ26: 500 | BK26: 500 | BL26: 500 | BM26: 500 | BN26: 500 | BO26: 500 | BP26: 500 | BQ26: 500 | BR26: 500 | BS26: 500 | BT26: 500 | BU26: 500 | BV26: 500
C28: Expansion Assumption
C29: Expansion | G29: # | I29: =SUMIFS($O29:$BV29,$O$22:$BV$22,I$22) -> 2329537.4 | J29: =SUMIFS($O29:$BV29,$O$22:$BV$22,J$22) -> 2335236.3 | K29: =SUMIFS($O29:$BV29,$O$22:$BV$22,K$22) -> 2346644.4 | L29: =SUMIFS($O29:$BV29,$O$22:$BV$22,L$22) -> 2347249.8 | M29: =SUMIFS($O29:$BV29,$O$22:$BV$22,M$22) -> 2347245.1 | O29: 178762.11 | P29: 173603.52 | Q29: 233465.2 | R29: 200328.63 | S29: 149405.29 | T29: 233644.93 | U29: 252277.53 | V29: 223411.45 | W29: 152917.62 | X29: 249669.6 | Y29: 151168.28 | Z29: 130883.26 | AA29: 189577.97 | AB29: 224186.78 | AC29: 136883.26 | AD29: 202167.4 | AE29: 220599.12 | AF29: 191235.24 | AG29: 194108.3 | AH29: 194863.35 | AI29: 189976.11 | AJ29: 198824.92 | AK29: 198267.84 | AL29: 194545.96 | AM29: 195097.75 | AN29: 195262.65 | AO29: 195329.21 | AP29: 196221.39 | AQ29: 195787.47 | AR29: 195374.07 | AS29: 195512.09 | AT29: 195581.15 | AU29: 195634.23 | AV29: 195685.06 | AW29: 195595.68 | AX29: 195563.71 | AY29: 195595.32 | AZ29: 195609.19 | BA29: 195613.86 | BB29: 195610.47 | BC29: 195598.04 | BD29: 195598.43 | BE29: 195604.22 | BF29: 195605.7 | BG29: 195605.12 | BH29: 195603.66 | BI29: 195602.53 | BJ29: 195603.28 | BK29: 195604.09 | BL29: 195604.06 | BM29: 195603.79 | BN29: 195603.57 | BO29: 195603.55 | BP29: 195603.72 | BQ29: 195603.8 | BR29: 195603.75 | BS29: 195603.7 | BT29: 195603.68 | BU29: 195603.7 | BV29: 195603.73
C31: Income statement assumptions
C32: Gross Margin | G32: % | I32: =iferror(AVERAGEIFS($O32:$BJ32,$O$22:$BJ$22,I$22),0) -> 0.8 | J32: =iferror(AVERAGEIFS($O32:$BJ32,$O$22:$BJ$22,J$22),0) -> 0.8 | K32: =iferror(AVERAGEIFS($O32:$BJ32,$O$22:$BJ$22,K$22),0) -> 0.8 | L32: =iferror(AVERAGEIFS($O32:$BJ32,$O$22:$BJ$22,L$22),0) -> 0.8 | M32: =iferror(AVERAGEIFS($O32:$BJ32,$O$22:$BJ$22,M$22),0) -> 0 | O32: 0.8 | P32: 0.8 | Q32: 0.8 | R32: 0.8 | S32: 0.8 | T32: 0.8 | U32: 0.8 | V32: 0.8 | W32: 0.8 | X32: 0.8 | Y32: 0.8 | Z32: 0.8 | AA32: 0.8 | AB32: 0.8 | AC32: 0.8 | AD32: 0.8 | AE32: 0.8 | AF32: 0.8 | AG32: 0.8 | AH32: 0.8 | AI32: 0.8 | AJ32: 0.8 | AK32: 0.8 | AL32: 0.8 | AM32: 0.8 | AN32: 0.8 | AO32: 0.8 | AP32: 0.8 | AQ32: 0.8 | AR32: 0.8 | AS32: 0.8 | AT32: 0.8 | AU32: 0.8 | AV32: 0.8 | AW32: 0.8 | AX32: 0.8 | AY32: 0.8 | AZ32: 0.8 | BA32: 0.8 | BB32: 0.8 | BC32: 0.8 | BD32: 0.8 | BE32: 0.8 | BF32: 0.8 | BG32: 0.8 | BH32: 0.8 | BI32: 0.8 | BJ32: 0.8 | BK32: 0.8 | BL32: 0.8 | BM32: 0.8 | BN32: 0.8 | BO32: 0.8 | BP32: 0.8 | BQ32: 0.8 | BR32: 0.8 | BS32: 0.8 | BT32: 0.8 | BU32: 0.8 | BV32: 0.8
C33: G&A | G33: $'000s | I33: =SUMIFS($O33:$BV33,$O$22:$BV$22,I$22) -> 3016.5551 | J33: =SUMIFS($O33:$BV33,$O$22:$BV$22,J$22) -> 3052.9535 | K33: =SUMIFS($O33:$BV33,$O$22:$BV$22,K$22) -> 3089.7912 | L33: =SUMIFS($O33:$BV33,$O$22:$BV$22,L$22) -> 3127.0733 | M33: =SUMIFS($O33:$BV33,$O$22:$BV$22,M$22) -> 3164.8052 | O33: =Actuals!N62 -> 250 | P33: =O33*1.001 -> 250.25 | Q33: =P33*1.001 -> 250.50025 | R33: =Q33*1.001 -> 250.75075 | S33: =R33*1.001 -> 251.0015 | T33: =S33*1.001 -> 251.2525 | U33: =T33*1.001 -> 251.50376 | V33: =U33*1.001 -> 251.75526 | W33: =V33*1.001 -> 252.00701 | ... BV33: =BU33*1.001 -> 265.18599
C34: S&M | G34: $'000s | I34: =SUMIFS($O34:$BV34,$O$22:$BV$22,I$22) -> 7239.7323 | J34: =SUMIFS($O34:$BV34,$O$22:$BV$22,J$22) -> 7327.0885 | K34: =SUMIFS($O34:$BV34,$O$22:$BV$22,K$22) -> 7415.4988 | L34: =SUMIFS($O34:$BV34,$O$22:$BV$22,L$22) -> 7504.9758 | M34: =SUMIFS($O34:$BV34,$O$22:$BV$22,M$22) -> 7595.5325 | O34: =Actuals!N63 -> 600 | P34: =O34*1.001 -> 600.6 | Q34: =P34*1.001 -> 601.2006 | R34: =Q34*1.001 -> 601.8018 | S34: =R34*1.001 -> 602.4036 | T34: =S34*1.001 -> 603.00601 | U34: =T34*1.001 -> 603.60901 | V34: =U34*1.001 -> 604.21262 | W34: =V34*1.001 -> 604.81683 | ... BV34: =BU34*1.001 -> 636.44638
C35: R&D | G35: $'000s | I35: =SUMIFS($O35:$BV35,$O$22:$BV$22,I$22) -> 4826.4882 | J35: =SUMIFS($O35:$BV35,$O$22:$BV$22,J$22) -> 4884.7257 | K35: =SUMIFS($O35:$BV35,$O$22:$BV$22,K$22) -> 4943.6658 | L35: =SUMIFS($O35:$BV35,$O$22:$BV$22,L$22) -> 5003.3172 | M35: =SUMIFS($O35:$BV35,$O$22:$BV$22,M$22) -> 5063.6883 | O35: =Actuals!N64 -> 400 | P35: =O35*1.001 -> 400.4 | Q35: =P35*1.001 -> 400.8004 | R35: =Q35*1.001 -> 401.2012 | S35: =R35*1.001 -> 401.6024 | T35: =S35*1.001 -> 402.004 | U35: =T35*1.001 -> 402.40601 | V35: =U35*1.001 -> 402.80841 | W35: =V35*1.001 -> 403.21122 | ... BV35: =BU35*1.001 -> 424.29759

Sheet Actuals
C2: Actuals SaaS Financial Model
C4: Notes
C5: 1. Enter your actuals in this sheet
C6: 2. Note for cohort metrics such as GRR and NRR, calculate the values as per the steps mentioned in this article and input the actuals here
H9: =IF(H17=1,"Actual","Forecast") -> Actual | I9: =IF(I17=1,"Actual","Forecast") -> Actual | J9: =IF(J17=1,"Actual","Forecast") -> Forecast | K9: =IF(K17=1,"Actual","Forecast") -> Forecast | L9: =IF(L17=1,"Actual","Forecast") -> Forecast | N9: =IF(N17=1,"Actual","Forecast") -> Actual | O9: =IF(O17=1,"Actual","Forecast") -> Actual | P9: =IF(P17=1,"Actual","Forecast") -> Actual | Q9: =IF(Q17=1,"Actual","Forecast") -> Actual | R9: =IF(R17=1,"Actual","Forecast") -> Actual | S9: =IF(S17=1,"Actual","Forecast") -> Actual | T9: =IF(T17=1,"Actual","Forecast") -> Actual | U9: =IF(U17=1,"Actual","Forecast") -> Actual | ... BU9: =IF(BU17=1,"Actual","Forecast") -> Forecast
H10: =H11 -> 44562 | I10: =I11 -> 44927 | J10: =J11 -> 45292 | K10: =K11 -> 45658 | L10: =L11 -> 46023 | N10: =N11 -> 44562 | O10: =O11 -> 44593 | P10: =P11 -> 44621 | Q10: =Q11 -> 44652 | R10: =R11 -> 44682 | S10: =S11 -> 44713 | T10: =T11 -> 44743 | U10: =U11 -> 44774 | ... BU10: =BU11 -> 46357
G11: Start of Period | H11: ='Key Assumptions'!D13 -> 44562 | I11: =H12+1 -> 44927 | J11: =I12+1 -> 45292 | K11: =J12+1 -> 45658 | L11: =K12+1 -> 46023 | N11: ='Key Assumptions'!D13 -> 44562 | O11: =N12+1 -> 44593 | P11: =O12+1 -> 44621 | Q11: =P12+1 -> 44652 | R11: =Q12+1 -> 44682 | S11: =R12+1 -> 44713 | T11: =S12+1 -> 44743 | U11: =T12+1 -> 44774 | V11: =U12+1 -> 44805 | ... BU11: =BT12+1 -> 46357
G12: End of Period | H12: =EOMONTH(H11,11) -> 44926 | I12: =EOMONTH(I11,11) -> 45291 | J12: =EOMONTH(J11,11) -> 45657 | K12: =EOMONTH(K11,11) -> 46022 | L12: =EOMONTH(L11,11) -> 46387 | N12: =EOMONTH(N11,0) -> 44592 | O12: =EOMONTH(O11,0) -> 44620 | P12: =EOMONTH(P11,0) -> 44651 | Q12: =EOMONTH(Q11,0) -> 44681 | R12: =EOMONTH(R11,0) -> 44712 | S12: =EOMONTH(S11,0) -> 44742 | T12: =EOMONTH(T11,0) -> 44773 | U12: =EOMONTH(U11,0) -> 44804 | ... BU12: =EOMONTH(BU11,0) -> 46387
G13: Timeline | H13: =IF(H12-H11>35,"Annual","Monthly") -> Annual | I13: =IF(I12-I11>35,"Annual","Monthly") -> Annual | J13: =IF(J12-J11>35,"Annual","Monthly") -> Annual | K13: =IF(K12-K11>35,"Annual","Monthly") -> Annual | L13: =IF(L12-L11>35,"Annual","Monthly") -> Annual | N13: =IF(N12-N11>35,"Annual","Monthly") -> Monthly | O13: =IF(O12-O11>35,"Annual","Monthly") -> Monthly | P13: =IF(P12-P11>35,"Annual","Monthly") -> Monthly | Q13: =IF(Q12-Q11>35,"Annual","Monthly") -> Monthly | R13: =IF(R12-R11>35,"Annual","Monthly") -> Monthly | S13: =IF(S12-S11>35,"Annual","Monthly") -> Monthly | T13: =IF(T12-T11>35,"Annual","Monthly") -> Monthly | U13: =IF(U12-U11>35,"Annual","Monthly") -> Monthly | ... BU13: =IF(BU12-BU11>35,"Annual","Monthly") -> Monthly
G14: Year | H14: =YEAR(H11) -> 2022 | I14: =YEAR(I11) -> 2023 | J14: =YEAR(J11) -> 2024 | K14: =YEAR(K11) -> 2025 | L14: =YEAR(L11) -> 2026 | N14: =YEAR(N11) -> 2022 | O14: =YEAR(O11) -> 2022 | P14: =YEAR(P11) -> 2022 | Q14: =YEAR(Q11) -> 2022 | R14: =YEAR(R11) -> 2022 | S14: =YEAR(S11) -> 2022 | T14: =YEAR(T11) -> 2022 | U14: =YEAR(U11) -> 2022 | ... BU14: =YEAR(BU11) -> 2026
G16: Flag
G17: Historical Flag | H17: =IF(AND(H11>='Key Assumptions'!$D$13,H11<'Key Assumptions'!$D$14),1,0) -> 1 | I17: =IF(AND(I11>='Key Assumptions'!$D$13,I11<'Key Assumptions'!$D$14),1,0) -> 1 | J17: =IF(AND(J11>='Key Assumptions'!$D$13,J11<'Key Assumptions'!$D$14),1,0) -> 0 | K17: =IF(AND(K11>='Key Assumptions'!$D$13,K11<'Key Assumptions'!$D$14),1,0) -> 0 | L17: =IF(AND(L11>='Key Assumptions'!$D$13,L11<'Key Assumptions'!$D$14),1,0) -> 0 | N17: =IF(AND(N11>='Key Assumptions'!$D$13,N11<'Key Assumptions'!$D$14),1,0) -> 1 | O17: =IF(AND(O11>='Key Assumptions'!$D$13,O11<'Key Assumptions'!$D$14),1,0) -> 1 | P17: =IF(AND(P11>='Key Assumptions'!$D$13,P11<'Key Assumptions'!$D$14),1,0) -> 1 | Q17: =IF(AND(Q11>='Key Assumptions'!$D$13,Q11<'Key Assumptions'!$D$14),1,0) -> 1 | R17: =IF(AND(R11>='Key Assumptions'!$D$13,R11<'Key Assumptions'!$D$14),1,0) -> 1 | S17: =IF(AND(S11>='Key Assumptions'!$D$13,S11<'Key Assumptions'!$D$14),1,0) -> 1 | T17: =IF(AND(T11>='Key Assumptions'!$D$13,T11<'Key Assumptions'!$D$14),1,0) -> 1 | U17: =IF(AND(U11>='Key Assumptions'!$D$13,U11<'Key Assumptions'!$D$14),1,0) -> 1 | ... BU17: =IF(AND(BU11>='Key Assumptions'!$D$13,BU11<'Key Assumptions'!$D$14),1,0) -> 0
G18: Forecast Flag | H18: =IF(AND(H11>='Key Assumptions'!$D$15,H11<'Key Assumptions'!$D$16),1,0) -> 0 | I18: =IF(AND(I11>='Key Assumptions'!$D$15,I11<'Key Assumptions'!$D$16),1,0) -> 0 | J18: =IF(AND(J11>='Key Assumptions'!$D$15,J11<'Key Assumptions'!$D$16),1,0) -> 1 | K18: =IF(AND(K11>='Key Assumptions'!$D$15,K11<'Key Assumptions'!$D$16),1,0) -> 1 | L18: =IF(AND(L11>='Key Assumptions'!$D$15,L11<'Key Assumptions'!$D$16),1,0) -> 1 | N18: =IF(AND(N11>='Key Assumptions'!$D$15,N11<'Key Assumptions'!$D$16),1,0) -> 0 | O18: =IF(AND(O11>='Key Assumptions'!$D$15,O11<'Key Assumptions'!$D$16),1,0) -> 0 | P18: =IF(AND(P11>='Key Assumptions'!$D$15,P11<'Key Assumptions'!$D$16),1,0) -> 0 | Q18: =IF(AND(Q11>='Key Assumptions'!$D$15,Q11<'Key Assumptions'!$D$16),1,0) -> 0 | R18: =IF(AND(R11>='Key Assumptions'!$D$15,R11<'Key Assumptions'!$D$16),1,0) -> 0 | S18: =IF(AND(S11>='Key Assumptions'!$D$15,S11<'Key Assumptions'!$D$16),1,0) -> 0 | T18: =IF(AND(T11>='Key Assumptions'!$D$15,T11<'Key Assumptions'!$D$16),1,0) -> 0 | U18: =IF(AND(U11>='Key Assumptions'!$D$15,U11<'Key Assumptions'!$D$16),1,0) -> 0 | ... BU18: =IF(AND(BU11>='Key Assumptions'!$D$15,BU11<'Key Assumptions'!$D$16),1,0) -> 1
G19: Year Flag | H19: =COUNTA($H$11:H11) -> 1 | I19: =COUNTA($H$11:I11) -> 2 | J19: =COUNTA($H$11:J11) -> 3 | K19: =COUNTA($H$11:K11) -> 4 | L19: =COUNTA($H$11:L11) -> 5 | N19: =INDEX($H$19:$L$19,MATCH(YEAR(N$11),$H$14:$L$14,0)) -> 1 | O19: =INDEX($H$19:$L$19,MATCH(YEAR(O$11),$H$14:$L$14,0)) -> 1 | P19: =INDEX($H$19:$L$19,MATCH(YEAR(P$11),$H$14:$L$14,0)) -> 1 | Q19: =INDEX($H$19:$L$19,MATCH(YEAR(Q$11),$H$14:$L$14,0)) -> 1 | R19: =INDEX($H$19:$L$19,MATCH(YEAR(R$11),$H$14:$L$14,0)) -> 1 | S19: =INDEX($H$19:$L$19,MATCH(YEAR(S$11),$H$14:$L$14,0)) -> 1 | T19: =INDEX($H$19:$L$19,MATCH(YEAR(T$11),$H$14:$L$14,0)) -> 1 | U19: =INDEX($H$19:$L$19,MATCH(YEAR(U$11),$H$14:$L$14,0)) -> 1 | ... BU19: =INDEX($H$19:$L$19,MATCH(YEAR(BU$11),$H$14:$L$14,0)) -> 5
C21: ARR Summary
C22: Beginning ARR | G22: $ | H22: =INDEX($N22:$BU22,MATCH(H$11,$N$11:$BU$11,0)) -> 11935000 | I22: =INDEX($N22:$BU22,MATCH(I$11,$N$11:$BU$11,0)) -> 17099065 | J22: =INDEX($N22:$BU22,MATCH(J$11,$N$11:$BU$11,0)) | K22: =INDEX($N22:$BU22,MATCH(K$11,$N$11:$BU$11,0)) | L22: =INDEX($N22:$BU22,MATCH(L$11,$N$11:$BU$11,0)) | N22: 11935000 | O22: =N26 -> 12248800 | P22: =O26 -> 12691380 | Q22: =P26 -> 13205436 | R22: =Q26 -> 13595598 | S22: =R26 -> 13929304 | T22: =S26 -> 14504143 | U22: =T26 -> 15198474 | V22: =U26 -> 15699593 | ... AE22: =AD26 -> 19266078
C23: New ARR | G23: $ | H23: =SUMIFS($N23:$BU23,$N$19:$BU$19,H$19) -> 5288050 | I23: =SUMIFS($N23:$BU23,$N$19:$BU$19,I$19) -> 2643755 | J23: =SUMIFS($N23:$BU23,$N$19:$BU$19,J$19) -> 0 | K23: =SUMIFS($N23:$BU23,$N$19:$BU$19,K$19) -> 0 | L23: =SUMIFS($N23:$BU23,$N$19:$BU$19,L$19) -> 0 | N23: 405790 | O23: 394080 | P23: 529966 | Q23: 454746 | R23: 339150 | S23: 530374 | T23: 572670 | U23: 507144 | V23: 347123 | W23: 566750 | X23: 343152 | Y23: 297105 | Z23: 430342 | AA23: 508904 | AB23: 310725 | AC23: 458920 | AD23: 500760 | AE23: 434104
C24: Expansion ARR | G24: $ | H24: =SUMIFS($N24:$BU24,$N$19:$BU$19,H$19) -> 2329537.4 | I24: =SUMIFS($N24:$BU24,$N$19:$BU$19,I$19) -> 1164649.8 | J24: =SUMIFS($N24:$BU24,$N$19:$BU$19,J$19) -> 0 | K24: =SUMIFS($N24:$BU24,$N$19:$BU$19,K$19) -> 0 | L24: =SUMIFS($N24:$BU24,$N$19:$BU$19,L$19) -> 0 | N24: 178762.11 | O24: 173603.52 | P24: 233465.2 | Q24: 200328.63 | R24: 149405.29 | S24: 233644.93 | T24: 252277.53 | U24: 223411.45 | V24: 152917.62 | W24: 249669.6 | X24: 151168.28 | Y24: 130883.26 | Z24: 189577.97 | AA24: 224186.78 | AB24: 136883.26 | AC24: 202167.4 | AD24: 220599.12 | AE24: 191235.24
C25: Churn ARR | G25: $ | H25: =SUMIFS($N25:$BU25,$N$19:$BU$19,H$19) -> -2453522 | I25: =SUMIFS($N25:$BU25,$N$19:$BU$19,I$19) -> -1314525 | J25: =SUMIFS($N25:$BU25,$N$19:$BU$19,J$19) -> 0 | K25: =SUMIFS($N25:$BU25,$N$19:$BU$19,K$19) -> 0 | L25: =SUMIFS($N25:$BU25,$N$19:$BU$19,L$19) -> 0 | N25: -270752 | O25: -125104 | P25: -249375 | Q25: -264912 | R25: -154850 | S25: -189180 | T25: -130616 | U25: -229437 | V25: -201654 | W25: -252300 | X25: -252830 | Y25: -132512 | Z25: -107376 | AA25: -136936 | AB25: -202352 | AC25: -269773 | AD25: -299616 | AE25: -298472
C26: Ending ARR | G26: $ | H26: =INDEX($N26:$BU26,MATCH(H$12,N$12:$BU$12,0)) -> 17099065 | I26: =INDEX($N26:$BU26,MATCH(I$12,O$12:$BU$12,0)) | J26: =INDEX($N26:$BU26,MATCH(J$12,P$12:$BU$12,0)) | K26: =INDEX($N26:$BU26,MATCH(K$12,Q$12:$BU$12,0)) | L26: =INDEX($N26:$BU26,MATCH(L$12,R$12:$BU$12,0)) | N26: =SUM(N22:N25) -> 12248800 | O26: =SUM(O22:O25) -> 12691380 | P26: =SUM(P22:P25) -> 13205436 | Q26: =SUM(Q22:Q25) -> 13595598 | R26: =SUM(R22:R25) -> 13929304 | S26: =SUM(S22:S25) -> 14504143 | T26: =SUM(T22:T25) -> 15198474 | U26: =SUM(U22:U25) -> 15699593 | ... AE26: =SUM(AE22:AE25) -> 19592945
C28: Customer Summary
C29: Beginning Customers | G29: $ | H29: =SUMIFS($N29:$BI29,$N$19:$BI$19,H$19) -> 6817 | I29: =SUMIFS($N29:$BI29,$N$19:$BI$19,I$19) -> 4045 | J29: =SUMIFS($N29:$BI29,$N$19:$BI$19,J$19) -> 0 | K29: =SUMIFS($N29:$BI29,$N$19:$BI$19,K$19) -> 0 | L29: =SUMIFS($N29:$BI29,$N$19:$BI$19,L$19) -> 0 | N29: 500 | O29: =N32 -> 509 | P29: =O32 -> 519 | Q29: =P32 -> 531 | R29: =Q32 -> 543 | S29: =R32 -> 556 | T29: =S32 -> 576 | U29: =T32 -> 595 | V29: =U32 -> 606 | ... AE29: =AD32 -> 704
C30: New Customers | G30: $ | H30: =SUMIFS($N30:$BI30,$N$19:$BI$19,H$19) -> 248 | I30: =SUMIFS($N30:$BI30,$N$19:$BI$19,I$19) -> 126 | J30: =SUMIFS($N30:$BI30,$N$19:$BI$19,J$19) -> 0 | K30: =SUMIFS($N30:$BI30,$N$19:$BI$19,K$19) -> 0 | L30: =SUMIFS($N30:$BI30,$N$19:$BI$19,L$19) -> 0 | N30: =N41 -> 16 | O30: =O41 -> 21 | P30: =P41 -> 23 | Q30: =Q41 -> 19 | R30: =R41 -> 18 | S30: =S41 -> 28 | T30: =T41 -> 25 | U30: =U41 -> 23 | ... AE30: =AE41 -> 23
C31: Churned Customers | G31: $ | H31: =SUMIFS($N31:$BI31,$N$19:$BI$19,H$19) -> -100 | I31: =SUMIFS($N31:$BI31,$N$19:$BI$19,I$19) -> -58 | J31: =SUMIFS($N31:$BI31,$N$19:$BI$19,J$19) -> 0 | K31: =SUMIFS($N31:$BI31,$N$19:$BI$19,K$19) -> 0 | L31: =SUMIFS($N31:$BI31,$N$19:$BI$19,L$19) -> 0 | N31: =-N49 -> -7 | O31: =-O49 -> -11 | P31: =-P49 -> -11 | Q31: =-Q49 -> -7 | R31: =-R49 -> -5 | S31: =-S49 -> -8 | T31: =-T49 -> -6 | U31: =-U49 -> -12 | ... AE31: =-AE49 -> -11
C32: Ending Customers | G32: $ | H32: =SUMIFS($N32:$BI32,$N$19:$BI$19,H$19) -> 6965 | I32: =SUMIFS($N32:$BI32,$N$19:$BI$19,I$19) -> 4113 | J32: =SUMIFS($N32:$BI32,$N$19:$BI$19,J$19) -> 0 | K32: =SUMIFS($N32:$BI32,$N$19:$BI$19,K$19) -> 0 | L32: =SUMIFS($N32:$BI32,$N$19:$BI$19,L$19) -> 0 | N32: =SUM(N29:N31) -> 509 | O32: =SUM(O29:O31) -> 519 | P32: =SUM(P29:P31) -> 531 | Q32: =SUM(Q29:Q31) -> 543 | R32: =SUM(R29:R31) -> 556 | S32: =SUM(S29:S31) -> 576 | T32: =SUM(T29:T31) -> 595 | U32: =SUM(U29:U31) -> 606 | ... AE32: =SUM(AE29:AE31) -> 716
C34: Average Contract Value Summary
C35: Historical ACV | G35: $ | H35: =iferror(AVERAGEIFS($N35:$BI35,$N$19:$BI$19,H$19),0) -> 25431.513 | I35: =iferror(AVERAGEIFS($N35:$BI35,$N$19:$BI$19,I$19),0) -> 27219.758 | J35: =iferror(AVERAGEIFS($N35:$BI35,$N$19:$BI$19,J$19),0) -> 0 | K35: =iferror(AVERAGEIFS($N35:$BI35,$N$19:$BI$19,K$19),0) -> 0 | L35: =iferror(AVERAGEIFS($N35:$BI35,$N$19:$BI$19,L$19),0) -> 0 | N35: =N26/N32 -> 24064.44 | O35: =O26/O32 -> 24453.525 | P35: =P26/P32 -> 24868.994 | Q35: =Q26/Q32 -> 25037.935 | R35: =R26/R32 -> 25052.705 | S35: =S26/S32 -> 25180.803 | T35: =T26/T32 -> 25543.654 | U35: =U26/U32 -> 25906.919 | ... AE35: =AE26/AE32 -> 27364.449
C37: New Customers Calculation
C38: Pipeline Leads | G38: # | H38: =SUMIFS($N38:$BI38,$N$19:$BI$19,H$19) -> 6108 | I38: =SUMIFS($N38:$BI38,$N$19:$BI$19,I$19) -> 2986 | J38: =SUMIFS($N38:$BI38,$N$19:$BI$19,J$19) -> 0 | K38: =SUMIFS($N38:$BI38,$N$19:$BI$19,K$19) -> 0 | L38: =SUMIFS($N38:$BI38,$N$19:$BI$19,L$19) -> 0 | N38: 466 | O38: 534 | P38: 485 | Q38: 507 | R38: 515 | S38: 542 | T38: 466 | U38: 541 | V38: 536 | W38: 469 | X38: 525 | Y38: 522 | Z38: 508 | AA38: 450 | AB38: 450 | AC38: 520 | AD38: 531 | AE38: 527
C39: MQL | G39: # | H39: =SUMIFS($N39:$BI39,$N$19:$BI$19,H$19) -> 787 | I39: =SUMIFS($N39:$BI39,$N$19:$BI$19,I$19) -> 395 | J39: =SUMIFS($N39:$BI39,$N$19:$BI$19,J$19) -> 0 | K39: =SUMIFS($N39:$BI39,$N$19:$BI$19,K$19) -> 0 | L39: =SUMIFS($N39:$BI39,$N$19:$BI$19,L$19) -> 0 | N39: 61 | O39: 80 | P39: 68 | Q39: 61 | R39: 62 | S39: 76 | T39: 70 | U39: 70 | V39: 54 | W39: 70 | X39: 63 | Y39: 52 | Z39: 71 | AA39: 54 | AB39: 54 | AC39: 78 | AD39: 69 | AE39: 69
C40: SQL | G40: # | H40: =SUMIFS($N40:$BI40,$N$19:$BI$19,H$19) -> 353 | I40: =SUMIFS($N40:$BI40,$N$19:$BI$19,I$19) -> 179 | J40: =SUMIFS($N40:$BI40,$N$19:$BI$19,J$19) -> 0 | K40: =SUMIFS($N40:$BI40,$N$19:$BI$19,K$19) -> 0 | L40: =SUMIFS($N40:$BI40,$N$19:$BI$19,L$19) -> 0 | N40: 22 | O40: 31 | P40: 31 | Q40: 28 | R40: 24 | S40: 41 | T40: 37 | U40: 33 | V40: 25 | W40: 36 | X40: 23 | Y40: 22 | Z40: 33 | AA40: 27 | AB40: 19 | AC40: 28 | AD40: 38 | AE40: 34
C41: Deals / New Customers | G41: # | H41: =SUMIFS($N41:$BI41,$N$19:$BI$19,H$19) -> 248 | I41: =SUMIFS($N41:$BI41,$N$19:$BI$19,I$19) -> 126 | J41: =SUMIFS($N41:$BI41,$N$19:$BI$19,J$19) -> 0 | K41: =SUMIFS($N41:$BI41,$N$19:$BI$19,K$19) -> 0 | L41: =SUMIFS($N41:$BI41,$N$19:$BI$19,L$19) -> 0 | N41: 16 | O41: 21 | P41: 23 | Q41: 19 | R41: 18 | S41: 28 | T41: 25 | U41: 23 | V41: 19 | W41: 23 | X41: 17 | Y41: 16 | Z41: 22 | AA41: 20 | AB41: 13 | AC41: 21 | AD41: 27 | AE41: 23
C43: Pipeline to MQL (conversion rate %) | G43: % | H43: =iferror(AVERAGEIFS($N43:$BI43,$N$19:$BI$19,H$19),0) -> 0.12925558 | I43: =iferror(AVERAGEIFS($N43:$BI43,$N$19:$BI$19,I$19),0) -> 0.13177285 | J43: =iferror(AVERAGEIFS($N43:$BI43,$N$19:$BI$19,J$19),0) -> 0 | K43: =iferror(AVERAGEIFS($N43:$BI43,$N$19:$BI$19,K$19),0) -> 0 | L43: =iferror(AVERAGEIFS($N43:$BI43,$N$19:$BI$19,L$19),0) -> 0 | N43: =N39/N38 -> 0.13090129 | O43: =O39/O38 -> 0.14981273 | P43: =P39/P38 -> 0.14020619 | Q43: =Q39/Q38 -> 0.12031558 | R43: =R39/R38 -> 0.12038835 | S43: =S39/S38 -> 0.1402214 | T43: =T39/T38 -> 0.15021459 | U43: =U39/U38 -> 0.12939002 | ... AE43: =AE39/AE38 -> 0.13092979
C44: MQL to SQL (conversion rate %) | G44: % | H44: =iferror(AVERAGEIFS($N44:$BI44,$N$19:$BI$19,H$19),0) -> 0.44625249 | I44: =iferror(AVERAGEIFS($N44:$BI44,$N$19:$BI$19,I$19),0) -> 0.4531822 | J44: =iferror(AVERAGEIFS($N44:$BI44,$N$19:$BI$19,J$19),0) -> 0 | K44: =iferror(AVERAGEIFS($N44:$BI44,$N$19:$BI$19,K$19),0) -> 0 | L44: =iferror(AVERAGEIFS($N44:$BI44,$N$19:$BI$19,L$19),0) -> 0 | N44: =N40/N39 -> 0.36065574 | O44: =O40/O39 -> 0.3875 | P44: =P40/P39 -> 0.45588235 | Q44: =Q40/Q39 -> 0.45901639 | R44: =R40/R39 -> 0.38709677 | S44: =S40/S39 -> 0.53947368 | T44: =T40/T39 -> 0.52857143 | U44: =U40/U39 -> 0.47142857 | ... AE44: =AE40/AE39 -> 0.49275362
C45: SQL to Deals (conversion rate %) | G45: % | H45: =iferror(AVERAGEIFS($N45:$BI45,$N$19:$BI$19,H$19),0) -> 0.70800527 | I45: =iferror(AVERAGEIFS($N45:$BI45,$N$19:$BI$19,I$19),0) -> 0.70476914 | J45: =iferror(AVERAGEIFS($N45:$BI45,$N$19:$BI$19,J$19),0) -> 0 | K45: =iferror(AVERAGEIFS($N45:$BI45,$N$19:$BI$19,K$19),0) -> 0 | L45: =iferror(AVERAGEIFS($N45:$BI45,$N$19:$BI$19,L$19),0) -> 0 | N45: =N41/N40 -> 0.72727273 | O45: =O41/O40 -> 0.67741935 | P45: =P41/P40 -> 0.74193548 | Q45: =Q41/Q40 -> 0.67857143 | R45: =R41/R40 -> 0.75 | S45: =S41/S40 -> 0.68292683 | T45: =T41/T40 -> 0.67567568 | U45: =U41/U40 -> 0.6969697 | ... AE45: =AE41/AE40 -> 0.67647059
C48: Churned Customers Calculation
C49: Historical / Forecasted Churn | G49: # | H49: =SUMIFS($N49:$BU49,$N$19:$BU$19,H$19) -> 100 | I49: =SUMIFS($N49:$BU49,$N$19:$BU$19,I$19) -> 58 | J49: =SUMIFS($N49:$BU49,$N$19:$BU$19,J$19) -> 0 | K49: =SUMIFS($N49:$BU49,$N$19:$BU$19,K$19) -> 0 | L49: =SUMIFS($N49:$BU49,$N$19:$BU$19,L$19) -> 0 | N49: 7 | O49: 11 | P49: 11 | Q49: 7 | R49: 5 | S49: 8 | T49: 6 | U49: 12 | V49: 10 | W49: 9 | X49: 8 | Y49: 6 | Z49: 12 | AA49: 6 | AB49: 9 | AC49: 10 | AD49: 10 | AE49: 11
C50: Churn Rate (% of total customer base) | G50: % | H50: =iferror(AVERAGEIFS($N50:$BI50,$N$19:$BI$19,H$19),0) -> 0.014785699 | I50: =iferror(AVERAGEIFS($N50:$BI50,$N$19:$BI$19,I$19),0) -> 0.014333976 | J50: =iferror(AVERAGEIFS($N50:$BI50,$N$19:$BI$19,J$19),0) -> 0 | K50: =iferror(AVERAGEIFS($N50:$BI50,$N$19:$BI$19,K$19),0) -> 0 | L50: =iferror(AVERAGEIFS($N50:$BI50,$N$19:$BI$19,L$19),0) -> 0 | N50: =N49/N29 -> 0.014 | O50: =O49/O29 -> 0.021611002 | P50: =P49/P29 -> 0.021194605 | Q50: =Q49/Q29 -> 0.013182674 | R50: =R49/R29 -> 0.0092081031 | S50: =S49/S29 -> 0.014388489 | T50: =T49/T29 -> 0.010416667 | U50: =U49/U29 -> 0.020168067 | ... AE50: =AE49/AE29 -> 0.015625
C53: P&L
C54: Revenue | G54: $'000s | H54: =SUMIFS($N54:$BU54,$N$19:$BU$19,H$19) -> 13273.974 | I54: =SUMIFS($N54:$BU54,$N$19:$BU$19,I$19) -> 7487.8048 | J54: =SUMIFS($N54:$BU54,$N$19:$BU$19,J$19) -> 0 | K54: =SUMIFS($N54:$BU54,$N$19:$BU$19,K$19) -> 0 | L54: =SUMIFS($N54:$BU54,$N$19:$BU$19,L$19) -> 0 | N54: 997.50317 | O54: 1019.9178 | P54: 1043.3004 | Q54: 1059.1199 | R54: 1074.4782 | S54: 1102.9111 | T54: 1139.7489 | U54: 1162.8912 | V54: 1158.3469 | W54: 1167.8844 | X54: 1167.0779 | Y54: 1180.794 | Z54: 1207.7078 | AA54: 1238.7052 | AB54: 1239.4029 | AC54: 1255.1652 | AD54: 1271.9272 | AE54: 1274.8965
C55: Revenue Growth | G55: % | H55: =IFERROR(H54/G54-1,0) -> 0 | I55: =IFERROR(I54/H54-1,0) -> -0.43590331 | J55: =IFERROR(J54/I54-1,0) -> -1 | K55: =IFERROR(K54/J54-1,0) -> 0 | L55: =IFERROR(L54/K54-1,0) -> 0 | N55: =IFERROR(N54/M54-1,0) -> 0 | O55: =IFERROR(O54/N54-1,0) -> 0.022470772 | P55: =IFERROR(P54/O54-1,0) -> 0.022925948 | Q55: =IFERROR(Q54/P54-1,0) -> 0.015162938 | R55: =IFERROR(R54/Q54-1,0) -> 0.014501033 | S55: =IFERROR(S54/R54-1,0) -> 0.026461991 | T55: =IFERROR(T54/S54-1,0) -> 0.033400547 | U55: =IFERROR(U54/T54-1,0) -> 0.020304691 | ... AE55: =IFERROR(AE54/AD54-1,0) -> 0.0023345152
C57: COGS | G57: $'000s | H57: =SUMIFS($N57:$BU57,$N$19:$BU$19,H$19) -> -2654.7948 | I57: =SUMIFS($N57:$BU57,$N$19:$BU$19,I$19) -> -1497.561 | J57: =SUMIFS($N57:$BU57,$N$19:$BU$19,J$19) -> 0 | K57: =SUMIFS($N57:$BU57,$N$19:$BU$19,K$19) -> 0 | L57: =SUMIFS($N57:$BU57,$N$19:$BU$19,L$19) -> 0 | N57: -199.50063 | O57: -203.98357 | P57: -208.66008 | Q57: -211.82398 | R57: -214.89565 | S57: -220.58222 | T57: -227.94978 | U57: -232.57823 | V57: -231.66938 | W57: -233.57688 | X57: -233.41558 | Y57: -236.1588 | Z57: -241.54157 | AA57: -247.74103 | AB57: -247.88058 | AC57: -251.03303 | AD57: -254.38543 | AE57: -254.9793
C58: Gross Profit | G58: $'000s | H58: =H54+H57 -> 10619.179 | I58: =I54+I57 -> 5990.2438 | J58: =J54+J57 -> 0 | K58: =K54+K57 -> 0 | L58: =L54+L57 -> 0 | N58: =N54+N57 -> 798.00253 | O58: =O54+O57 -> 815.93427 | P58: =P54+P57 -> 834.64033 | Q58: =Q54+Q57 -> 847.29593 | R58: =R54+R57 -> 859.5826 | S58: =S54+S57 -> 882.32887 | T58: =T54+T57 -> 911.79913 | U58: =U54+U57 -> 930.31293 | ... BU58: =BU54+BU57 -> 0
C59: Gross Margin | H59: =iferror(H58/H54,0) -> 0.8 | I59: =iferror(I58/I54,0) -> 0.8 | J59: =iferror(J58/J54,0) -> 0 | K59: =iferror(K58/K54,0) -> 0 | L59: =iferror(L58/L54,0) -> 0 | N59: 0.8 | O59: 0.8 | P59: 0.8 | Q59: 0.8 | R59: 0.8 | S59: 0.8 | T59: 0.8 | U59: 0.8 | V59: 0.8 | W59: 0.8 | X59: 0.8 | Y59: 0.8 | Z59: 0.8 | AA59: 0.8 | AB59: 0.8 | AC59: 0.8 | AD59: 0.8 | AE59: 0.8
C61: Operating Expenses
C62: ='Key Assumptions'!C33 -> G&A | G62: $'000s | H62: =SUMIFS($N62:$BU62,$N$19:$BU$19,H$19) -> 3000 | I62: =SUMIFS($N62:$BU62,$N$19:$BU$19,I$19) -> 1500 | J62: =SUMIFS($N62:$BU62,$N$19:$BU$19,J$19) -> 0 | K62: =SUMIFS($N62:$BU62,$N$19:$BU$19,K$19) -> 0 | L62: =SUMIFS($N62:$BU62,$N$19:$BU$19,L$19) -> 0 | N62: 250 | O62: 250 | P62: 250 | Q62: 250 | R62: 250 | S62: 250 | T62: 250 | U62: 250 | V62: 250 | W62: 250 | X62: 250 | Y62: 250 | Z62: 250 | AA62: 250 | AB62: 250 | AC62: 250 | AD62: 250 | AE62: 250
C63: ='Key Assumptions'!C34 -> S&M | G63: $'000s | H63: =SUMIFS($N63:$BU63,$N$19:$BU$19,H$19) -> 7200 | I63: =SUMIFS($N63:$BU63,$N$19:$BU$19,I$19) -> 3600 | J63: =SUMIFS($N63:$BU63,$N$19:$BU$19,J$19) -> 0 | K63: =SUMIFS($N63:$BU63,$N$19:$BU$19,K$19) -> 0 | L63: =SUMIFS($N63:$BU63,$N$19:$BU$19,L$19) -> 0 | N63: 600 | O63: 600 | P63: 600 | Q63: 600 | R63: 600 | S63: 600 | T63: 600 | U63: 600 | V63: 600 | W63: 600 | X63: 600 | Y63: 600 | Z63: 600 | AA63: 600 | AB63: 600 | AC63: 600 | AD63: 600 | AE63: 600
C64: ='Key Assumptions'!C35 -> R&D | G64: $'000s | H64: =SUMIFS($N64:$BU64,$N$19:$BU$19,H$19) -> 4800 | I64: =SUMIFS($N64:$BU64,$N$19:$BU$19,I$19) -> 2400 | J64: =SUMIFS($N64:$BU64,$N$19:$BU$19,J$19) -> 0 | K64: =SUMIFS($N64:$BU64,$N$19:$BU$19,K$19) -> 0 | L64: =SUMIFS($N64:$BU64,$N$19:$BU$19,L$19) -> 0 | N64: 400 | O64: 400 | P64: 400 | Q64: 400 | R64: 400 | S64: 400 | T64: 400 | U64: 400 | V64: 400 | W64: 400 | X64: 400 | Y64: 400 | Z64: 400 | AA64: 400 | AB64: 400 | AC64: 400 | AD64: 400 | AE64: 400
C65: Total Operating Expenses | G65: $'000s | H65: =sum(H62:H64) -> 15000 | I65: =sum(I62:I64) -> 7500 | J65: =sum(J62:J64) -> 0 | K65: =sum(K62:K64) -> 0 | L65: =sum(L62:L64) -> 0 | N65: =sum(N62:N64) -> 1250 | O65: =sum(O62:O64) -> 1250 | P65: =sum(P62:P64) -> 1250 | Q65: =sum(Q62:Q64) -> 1250 | R65: =sum(R62:R64) -> 1250 | S65: =sum(S62:S64) -> 1250 | T65: =sum(T62:T64) -> 1250 | U65: =sum(U62:U64) -> 1250 | ... AE65: =sum(AE62:AE64) -> 1250
C67: EBITDA | G67: $'000s | H67: =H58-H65 -> -4380.8208 | I67: =I58-I65 -> -1509.7562 | J67: =J58-J65 -> 0 | K67: =K58-K65 -> 0 | L67: =L58-L65 -> 0 | N67: =N58-N65 -> -451.99747 | O67: =O58-O65 -> -434.06573 | P67: =P58-P65 -> -415.35967 | Q67: =Q58-Q65 -> -402.70407 | R67: =R58-R65 -> -390.4174 | S67: =S58-S65 -> -367.67113 | T67: =T58-T65 -> -338.20087 | U67: =U58-U65 -> -319.68707 | ... AE67: =AE58-AE65 -> -230.0828
C68: EBITDA Margin | G68: % | H68: =iferror(H67/H54,0) -> -0.33003084 | I68: =iferror(I67/I54,0) -> -0.20162868 | J68: =iferror(J67/J54,0) -> 0 | K68: =iferror(K67/K54,0) -> 0 | L68: =iferror(L67/L54,0) -> 0 | N68: =N67/N54 -> -0.45312885 | O68: =O67/O54 -> -0.42558892 | P68: =P67/P54 -> -0.39812087 | Q68: =Q67/Q54 -> -0.38022519 | R68: =R67/R54 -> -0.36335533 | S68: =S67/S54 -> -0.33336426 | T68: =T67/T54 -> -0.29673278 | U68: =U67/U54 -> -0.27490712 | ... AE68: =AE67/AE54 -> -0.18047175
C70: SaaS metrics
C71: Customers Available to Renew | G71: # | H71: =SUMIFS($N71:$BU71,$N$19:$BU$19,H$19) -> 395 | I71: =SUMIFS($N71:$BU71,$N$18:$BU$18,I$18) -> 596 | J71: =SUMIFS($N71:$BU71,$N$18:$BU$18,J$18) -> 0 | K71: =SUMIFS($N71:$BU71,$N$18:$BU$18,K$18) -> 0 | L71: =SUMIFS($N71:$BU71,$N$18:$BU$18,L$18) -> 0 | N71: 32 | O71: 41 | P71: 42 | Q71: 27 | R71: 35 | S71: 34 | T71: 39 | U71: 33 | V71: 30 | W71: 30 | X71: 27 | Y71: 25 | Z71: 36 | AA71: 29 | AB71: 27 | AC71: 30 | AD71: 38 | AE71: 41
C72: ARR Available to Renew | G72: # | H72: =SUMIFS($N72:$BU72,$N$18:$BU$18,H$18) -> 14872145 | I72: =SUMIFS($N72:$BU72,$N$18:$BU$18,I$18) -> 14872145 | J72: =SUMIFS($N72:$BU72,$N$18:$BU$18,J$18) -> 0 | K72: =SUMIFS($N72:$BU72,$N$18:$BU$18,K$18) -> 0 | L72: =SUMIFS($N72:$BU72,$N$18:$BU$18,L$18) -> 0 | N72: 760857.5 | O72: 738900 | P72: 993687.5 | Q72: 852650 | R72: 635907.5 | S72: 994452.5 | T72: 1073757.5 | U72: 950895 | V72: 650855 | W72: 1062657.5 | X72: 643410 | Y72: 557072.5 | Z72: 806892.5 | AA72: 954195 | AB72: 582610 | AC72: 860475 | AD72: 938925 | AE72: 813945
C73: Customer Retention | G73: % | H73: =(H71-H49)/H71 -> 0.74683544 | I73: =(I71-I49)/I71 -> 0.90268456 | J73: =SUMIFS($N73:$BU73,$N$18:$BU$18,J$18) -> 0 | K73: =SUMIFS($N73:$BU73,$N$18:$BU$18,K$18) -> 0 | L73: =SUMIFS($N73:$BU73,$N$18:$BU$18,L$18) -> 0 | N73: =(N71-N49)/N71 -> 0.78125 | O73: =(O71-O49)/O71 -> 0.73170732 | P73: =(P71-P49)/P71 -> 0.73809524 | Q73: =(Q71-Q49)/Q71 -> 0.74074074 | R73: =(R71-R49)/R71 -> 0.85714286 | S73: =(S71-S49)/S71 -> 0.76470588 | T73: =(T71-T49)/T71 -> 0.84615385 | U73: =(U71-U49)/U71 -> 0.63636364 | ... AE73: =(AE71-AE49)/AE71 -> 0.73170732
C74: Gross Dollar Retention (GRR) | G74: % | H74: 0.7366 | I74: 0.7465 | J74: =SUMIFS($N74:$BU74,$N$18:$BU$18,J$18) -> 0 | K74: =SUMIFS($N74:$BU74,$N$18:$BU$18,K$18) -> 0 | L74: =SUMIFS($N74:$BU74,$N$18:$BU$18,L$18) -> 0 | N74: 0.77416089 | O74: 0.71439002 | P74: 0.6465856 | Q74: 0.72688936 | R74: 0.63821734 | S74: 0.86334371 | T74: 0.7727358 | U74: 0.67358338 | V74: 0.87507775 | W74: 0.74526478 | X74: 0.73667993 | Y74: 0.67210997 | Z74: 0.83700782 | AA74: 0.68232294 | AB74: 0.77221785 | AC74: 0.79106092 | AD74: 0.63108929 | AE74: 0.76515322
C75: Net Dollar Retention (NRR) | G75: % | H75: 1.1185 | I75: 1.1296 | J75: =SUMIFS($N75:$BU75,$N$18:$BU$18,J$18) -> 0 | K75: =SUMIFS($N75:$BU75,$N$18:$BU$18,K$18) -> 0 | L75: =SUMIFS($N75:$BU75,$N$18:$BU$18,L$18) -> 0 | N75: 1.1029474 | O75: 1.1537521 | P75: 1.2498159 | Q75: 1.0214469 | R75: 1.0383119 | S75: 1.0357644 | T75: 1.1883622 | U75: 1.0136102 | V75: 1.1807708 | W75: 1.0744301 | X75: 1.1369218 | Y75: 1.2262531 | Z75: 1.0399546 | AA75: 1.1404046 | AB75: 1.1233209 | AC75: 1.2399628 | AD75: 1.0913539 | AE75: 1.1427854
C77: Average Lifetime (in years) | G77: # | H77: =SUMIFS($N77:$BU77,$N$18:$BU$18,H$18) -> 71.709632 | I77: =SUMIFS($N77:$BU77,$N$18:$BU$18,I$18) -> 71.709632 | J77: =SUMIFS($N77:$BU77,$N$18:$BU$18,J$18) -> 0 | K77: =SUMIFS($N77:$BU77,$N$18:$BU$18,K$18) -> 0 | L77: =SUMIFS($N77:$BU77,$N$18:$BU$18,L$18) -> 0 | N77: =1/(1-N73) -> 4.5714286 | O77: =1/(1-O73) -> 3.7272727 | P77: =1/(1-P73) -> 3.8181818 | Q77: =1/(1-Q73) -> 3.8571429 | R77: =1/(1-R73) -> 7 | S77: =1/(1-S73) -> 4.25 | T77: =1/(1-T73) -> 6.5 | U77: =1/(1-U73) -> 2.75 | ... AE77: =1/(1-AE73) -> 3.7272727
C78: LTV | G78: $ | H78: =SUMIFS($N78:$BU78,$N$19:$BU$19,H$19) -> 1021595.8 | I78: =SUMIFS($N78:$BU78,$N$19:$BU$19,I$19) -> 465139.43 | J78: =SUMIFS($N78:$BU78,$N$18:$BU$18,J$18) -> 0 | K78: =SUMIFS($N78:$BU78,$N$18:$BU$18,K$18) -> 0 | L78: =SUMIFS($N78:$BU78,$N$18:$BU$18,L$18) -> 0 | N78: =N35*N59/(1-N73) -> 88007.096 | O78: =O35*O59/(1-O73) -> 72915.966 | P78: =P35*P59/(1-P73) -> 75963.473 | Q78: =Q35*Q59/(1-Q73) -> 77259.912 | R78: =R35*R59/(1-R73) -> 140295.15 | S78: =S35*S59/(1-S73) -> 85614.731 | T78: =T35*T59/(1-T73) -> 132827 | U78: =U35*U59/(1-U73) -> 56995.221 | ... AE78: =AE35*AE59/(1-AE73) -> 81595.81
C79: CAC | G79: $ | H79: =SUMIFS($N79:$BU79,$N$19:$BU$19,H$19) -> 359046.22 | I79: =SUMIFS($N79:$BU79,$N$19:$BU$19,I$19) -> 180307.18 | J79: =SUMIFS($N79:$BU79,$N$18:$BU$18,J$18) -> 0 | K79: =SUMIFS($N79:$BU79,$N$18:$BU$18,K$18) -> 0 | L79: =SUMIFS($N79:$BU79,$N$18:$BU$18,L$18) -> 0 | N79: =N63*1000/N30 -> 37500 | O79: =O63*1000/O30 -> 28571.429 | P79: =P63*1000/P30 -> 26086.957 | Q79: =Q63*1000/Q30 -> 31578.947 | R79: =R63*1000/R30 -> 33333.333 | S79: =S63*1000/S30 -> 21428.571 | T79: =T63*1000/T30 -> 24000 | U79: =U63*1000/U30 -> 26086.957 | ... AE79: =AE63*1000/AE30 -> 26086.957
C80: LTV to CAC Ratio | G80: # | H80: =H78/H79 -> 2.8453044 | I80: =I78/I79 -> 2.5797055 | J80: =SUMIFS($N80:$BU80,$N$18:$BU$18,J$18) -> 0 | K80: =SUMIFS($N80:$BU80,$N$18:$BU$18,K$18) -> 0 | L80: =SUMIFS($N80:$BU80,$N$18:$BU$18,L$18) -> 0 | N80: =N78/N79 -> 2.3468559 | O80: =O78/O79 -> 2.5520588 | P80: =P78/P79 -> 2.9119331 | Q80: =Q78/Q79 -> 2.4465639 | R80: =R78/R79 -> 4.2088544 | S80: =S78/S79 -> 3.9953541 | T80: =T78/T79 -> 5.5344584 | U80: =U78/U79 -> 2.1848168 | ... AE80: =AE78/AE79 -> 3.1278394

Sheet Summary
B2: Summary table SaaS Financial Model
G5: =IF(G13=1,"Actual","Forecast") -> Actual | H5: =IF(H13=1,"Actual","Forecast") -> Actual | I5: =IF(I13=1,"Actual","Forecast") -> Forecast | J5: =IF(J13=1,"Actual","Forecast") -> Forecast | K5: =IF(K13=1,"Actual","Forecast") -> Forecast | M5: =IF(M13=1,"Actual","Forecast") -> Actual | N5: =IF(N13=1,"Actual","Forecast") -> Actual | O5: =IF(O13=1,"Actual","Forecast") -> Actual | P5: =IF(P13=1,"Actual","Forecast") -> Actual | Q5: =IF(Q13=1,"Actual","Forecast") -> Actual | R5: =IF(R13=1,"Actual","Forecast") -> Actual | S5: =IF(S13=1,"Actual","Forecast") -> Actual | T5: =IF(T13=1,"Actual","Forecast") -> Actual | ... BT5: =IF(BT13=1,"Actual","Forecast") -> Forecast
G6: =G7 -> 44562 | H6: =H7 -> 44927 | I6: =I7 -> 45292 | J6: =J7 -> 45658 | K6: =K7 -> 46023 | M6: =M7 -> 44562 | N6: =N7 -> 44593 | O6: =O7 -> 44621 | P6: =P7 -> 44652 | Q6: =Q7 -> 44682 | R6: =R7 -> 44713 | S6: =S7 -> 44743 | T6: =T7 -> 44774 | ... BT6: =BT7 -> 46357
F7: Start Date | G7: ='Key Assumptions'!D13 -> 44562 | H7: =G8+1 -> 44927 | I7: =H8+1 -> 45292 | J7: =I8+1 -> 45658 | K7: =J8+1 -> 46023 | M7: ='Key Assumptions'!D13 -> 44562 | N7: =M8+1 -> 44593 | O7: =N8+1 -> 44621 | P7: =O8+1 -> 44652 | Q7: =P8+1 -> 44682 | R7: =Q8+1 -> 44713 | S7: =R8+1 -> 44743 | T7: =S8+1 -> 44774 | U7: =T8+1 -> 44805 | ... BT7: =BS8+1 -> 46357
F8: End Date | G8: =EOMONTH(G7,11) -> 44926 | H8: =EOMONTH(H7,11) -> 45291 | I8: =EOMONTH(I7,11) -> 45657 | J8: =EOMONTH(J7,11) -> 46022 | K8: =EOMONTH(K7,11) -> 46387 | M8: =EOMONTH(M7,0) -> 44592 | N8: =EOMONTH(N7,0) -> 44620 | O8: =EOMONTH(O7,0) -> 44651 | P8: =EOMONTH(P7,0) -> 44681 | Q8: =EOMONTH(Q7,0) -> 44712 | R8: =EOMONTH(R7,0) -> 44742 | S8: =EOMONTH(S7,0) -> 44773 | T8: =EOMONTH(T7,0) -> 44804 | ... BT8: =EOMONTH(BT7,0) -> 46387
F9: Timeline | G9: =IF(G8-G7>35,"Annual","Monthly") -> Annual | H9: =IF(H8-H7>35,"Annual","Monthly") -> Annual | I9: =IF(I8-I7>35,"Annual","Monthly") -> Annual | J9: =IF(J8-J7>35,"Annual","Monthly") -> Annual | K9: =IF(K8-K7>35,"Annual","Monthly") -> Annual | M9: =IF(M8-M7>35,"Annual","Monthly") -> Monthly | N9: =IF(N8-N7>35,"Annual","Monthly") -> Monthly | O9: =IF(O8-O7>35,"Annual","Monthly") -> Monthly | P9: =IF(P8-P7>35,"Annual","Monthly") -> Monthly | Q9: =IF(Q8-Q7>35,"Annual","Monthly") -> Monthly | R9: =IF(R8-R7>35,"Annual","Monthly") -> Monthly | S9: =IF(S8-S7>35,"Annual","Monthly") -> Monthly | T9: =IF(T8-T7>35,"Annual","Monthly") -> Monthly | ... BT9: =IF(BT8-BT7>35,"Annual","Monthly") -> Monthly
F10: Year | G10: =YEAR(G7) -> 2022 | H10: =YEAR(H7) -> 2023 | I10: =YEAR(I7) -> 2024 | J10: =YEAR(J7) -> 2025 | K10: =YEAR(K7) -> 2026 | M10: =YEAR(M7) -> 2022 | N10: =YEAR(N7) -> 2022 | O10: =YEAR(O7) -> 2022 | P10: =YEAR(P7) -> 2022 | Q10: =YEAR(Q7) -> 2022 | R10: =YEAR(R7) -> 2022 | S10: =YEAR(S7) -> 2022 | T10: =YEAR(T7) -> 2022 | ... BT10: =YEAR(BT7) -> 2026
F12: Flag
F13: Historical Flag | G13: =IF(AND(G7>='Key Assumptions'!$D$13,G7<'Key Assumptions'!$D$14),1,0) -> 1 | H13: =IF(AND(H7>='Key Assumptions'!$D$13,H7<'Key Assumptions'!$D$14),1,0) -> 1 | I13: =IF(AND(I7>='Key Assumptions'!$D$13,I7<'Key Assumptions'!$D$14),1,0) -> 0 | J13: =IF(AND(J7>='Key Assumptions'!$D$13,J7<'Key Assumptions'!$D$14),1,0) -> 0 | K13: =IF(AND(K7>='Key Assumptions'!$D$13,K7<'Key Assumptions'!$D$14),1,0) -> 0 | M13: =IF(AND(M7>='Key Assumptions'!$D$13,M7<'Key Assumptions'!$D$14),1,0) -> 1 | N13: =IF(AND(N7>='Key Assumptions'!$D$13,N7<'Key Assumptions'!$D$14),1,0) -> 1 | O13: =IF(AND(O7>='Key Assumptions'!$D$13,O7<'Key Assumptions'!$D$14),1,0) -> 1 | P13: =IF(AND(P7>='Key Assumptions'!$D$13,P7<'Key Assumptions'!$D$14),1,0) -> 1 | Q13: =IF(AND(Q7>='Key Assumptions'!$D$13,Q7<'Key Assumptions'!$D$14),1,0) -> 1 | R13: =IF(AND(R7>='Key Assumptions'!$D$13,R7<'Key Assumptions'!$D$14),1,0) -> 1 | S13: =IF(AND(S7>='Key Assumptions'!$D$13,S7<'Key Assumptions'!$D$14),1,0) -> 1 | T13: =IF(AND(T7>='Key Assumptions'!$D$13,T7<'Key Assumptions'!$D$14),1,0) -> 1 | ... BT13: =IF(AND(BT7>='Key Assumptions'!$D$13,BT7<'Key Assumptions'!$D$14),1,0) -> 0
F14: Forecast Flag | G14: =IF(AND(G7>='Key Assumptions'!$D$15,G7<'Key Assumptions'!$D$16),1,0) -> 0 | H14: =IF(AND(H7>='Key Assumptions'!$D$15,H7<'Key Assumptions'!$D$16),1,0) -> 0 | I14: =IF(AND(I7>='Key Assumptions'!$D$15,I7<'Key Assumptions'!$D$16),1,0) -> 1 | J14: =IF(AND(J7>='Key Assumptions'!$D$15,J7<'Key Assumptions'!$D$16),1,0) -> 1 | K14: =IF(AND(K7>='Key Assumptions'!$D$15,K7<'Key Assumptions'!$D$16),1,0) -> 1 | M14: =IF(AND(M7>='Key Assumptions'!$D$15,M7<'Key Assumptions'!$D$16),1,0) -> 0 | N14: =IF(AND(N7>='Key Assumptions'!$D$15,N7<'Key Assumptions'!$D$16),1,0) -> 0 | O14: =IF(AND(O7>='Key Assumptions'!$D$15,O7<'Key Assumptions'!$D$16),1,0) -> 0 | P14: =IF(AND(P7>='Key Assumptions'!$D$15,P7<'Key Assumptions'!$D$16),1,0) -> 0 | Q14: =IF(AND(Q7>='Key Assumptions'!$D$15,Q7<'Key Assumptions'!$D$16),1,0) -> 0 | R14: =IF(AND(R7>='Key Assumptions'!$D$15,R7<'Key Assumptions'!$D$16),1,0) -> 0 | S14: =IF(AND(S7>='Key Assumptions'!$D$15,S7<'Key Assumptions'!$D$16),1,0) -> 0 | T14: =IF(AND(T7>='Key Assumptions'!$D$15,T7<'Key Assumptions'!$D$16),1,0) -> 0 | ... BT14: =IF(AND(BT7>='Key Assumptions'!$D$15,BT7<'Key Assumptions'!$D$16),1,0) -> 1
F15: Year Flag | G15: =COUNTA($G$7:G7) -> 1 | H15: =COUNTA($G$7:H7) -> 2 | I15: =COUNTA($G$7:I7) -> 3 | J15: =COUNTA($G$7:J7) -> 4 | K15: =COUNTA($G$7:K7) -> 5 | M15: =INDEX($G$15:$K$15,MATCH(YEAR(M$7),$G$10:$K$10,0)) -> 1 | N15: =INDEX($G$15:$K$15,MATCH(YEAR(N$7),$G$10:$K$10,0)) -> 1 | O15: =INDEX($G$15:$K$15,MATCH(YEAR(O$7),$G$10:$K$10,0)) -> 1 | P15: =INDEX($G$15:$K$15,MATCH(YEAR(P$7),$G$10:$K$10,0)) -> 1 | Q15: =INDEX($G$15:$K$15,MATCH(YEAR(Q$7),$G$10:$K$10,0)) -> 1 | R15: =INDEX($G$15:$K$15,MATCH(YEAR(R$7),$G$10:$K$10,0)) -> 1 | S15: =INDEX($G$15:$K$15,MATCH(YEAR(S$7),$G$10:$K$10,0)) -> 1 | T15: =INDEX($G$15:$K$15,MATCH(YEAR(T$7),$G$10:$K$10,0)) -> 1 | ... BT15: =INDEX($G$15:$K$15,MATCH(YEAR(BT$7),$G$10:$K$10,0)) -> 5
B17: ARR Summary
B18: Beginning ARR | F18: $ | G18: =INDEX($M18:$BT18,MATCH(G$7,$M$7:$BT$7,0)) -> 11935000 | H18: =INDEX($M18:$BT18,MATCH(H$7,$M$7:$BT$7,0)) -> 17099065 | I18: =INDEX($M18:$BT18,MATCH(I$7,$M$7:$BT$7,0)) -> 22916197 | J18: =INDEX($M18:$BT18,MATCH(J$7,$M$7:$BT$7,0)) -> 29614278 | K18: =INDEX($M18:$BT18,MATCH(K$7,$M$7:$BT$7,0)) -> 36412072 | M18: =IF(M$13=1,Actuals!N22,L22) -> 11935000 | N18: =IF(N$13=1,Actuals!O22,M22) -> 12248800 | O18: =IF(O$13=1,Actuals!P22,N22) -> 12691380 | P18: =IF(P$13=1,Actuals!Q22,O22) -> 13205436 | Q18: =IF(Q$13=1,Actuals!R22,P22) -> 13595598 | R18: =IF(R$13=1,Actuals!S22,Q22) -> 13929304 | S18: =IF(S$13=1,Actuals!T22,R22) -> 14504143 | T18: =IF(T$13=1,Actuals!U22,S22) -> 15198474 | ... BT18: =IF(BT$13=1,Actuals!BU22,BS22) -> 42643185
B19: New ARR | F19: $ | G19: =SUMIFS($M19:$BT19,$M$15:$BT$15,G$15) -> 5288050 | H19: =SUMIFS($M19:$BT19,$M$15:$BT$15,H$15) -> 5764112.4 | I19: =SUMIFS($M19:$BT19,$M$15:$BT$15,I$15) -> 6240682.6 | J19: =SUMIFS($M19:$BT19,$M$15:$BT$15,J$15) -> 6240695.3 | K19: =SUMIFS($M19:$BT19,$M$15:$BT$15,K$15) -> 6240695.3 | M19: =IF(M$13=1,Actuals!N23,M$33*M28) -> 405790 | N19: =IF(N$13=1,Actuals!O23,N$33*N28) -> 394080 | O19: =IF(O$13=1,Actuals!P23,O$33*O28) -> 529966 | P19: =IF(P$13=1,Actuals!Q23,P$33*P28) -> 454746 | Q19: =IF(Q$13=1,Actuals!R23,Q$33*Q28) -> 339150 | R19: =IF(R$13=1,Actuals!S23,R$33*R28) -> 530374 | S19: =IF(S$13=1,Actuals!T23,S$33*S28) -> 572670 | T19: =IF(T$13=1,Actuals!U23,T$33*T28) -> 507144 | ... BT19: =IF(BT$13=1,Actuals!BU23,BT$33*BT28) -> 520057.94
B20: Expansion | F20: $ | G20: =SUMIFS($M20:$BT20,$M$15:$BT$15,G$15) -> 2329537.4 | H20: =SUMIFS($M20:$BT20,$M$15:$BT$15,H$15) -> 2335236.3 | I20: =SUMIFS($M20:$BT20,$M$15:$BT$15,I$15) -> 2346644.4 | J20: =SUMIFS($M20:$BT20,$M$15:$BT$15,J$15) -> 2347249.8 | K20: =SUMIFS($M20:$BT20,$M$15:$BT$15,K$15) -> 2347245.1 | M20: =IF(M$13=1,Actuals!N24,'Key Assumptions'!O29) -> 178762.11 | N20: =IF(N$13=1,Actuals!O24,'Key Assumptions'!P29) -> 173603.52 | O20: =IF(O$13=1,Actuals!P24,'Key Assumptions'!Q29) -> 233465.2 | P20: =IF(P$13=1,Actuals!Q24,'Key Assumptions'!R29) -> 200328.63 | Q20: =IF(Q$13=1,Actuals!R24,'Key Assumptions'!S29) -> 149405.29 | R20: =IF(R$13=1,Actuals!S24,'Key Assumptions'!T29) -> 233644.93 | S20: =IF(S$13=1,Actuals!T24,'Key Assumptions'!U29) -> 252277.53 | T20: =IF(T$13=1,Actuals!U24,'Key Assumptions'!V29) -> 223411.45 | ... BT20: =IF(BT$13=1,Actuals!BU24,'Key Assumptions'!BV29) -> 195603.73
B21: Churn ARR | F21: $ | G21: =SUMIFS($M21:$BT21,$M$15:$BT$15,G$15) -> -2453522 | H21: =SUMIFS($M21:$BT21,$M$15:$BT$15,H$15) -> -2282217.2 | I21: =SUMIFS($M21:$BT21,$M$15:$BT$15,I$15) -> -1889245.9 | J21: =SUMIFS($M21:$BT21,$M$15:$BT$15,J$15) -> -1790150.8 | K21: =SUMIFS($M21:$BT21,$M$15:$BT$15,K$15) -> -1790229.3 | M21: =IF(M$13=1,Actuals!N25,M$33*M29) -> -270752 | N21: =IF(N$13=1,Actuals!O25,N$33*N29) -> -125104 | O21: =IF(O$13=1,Actuals!P25,O$33*O29) -> -249375 | P21: =IF(P$13=1,Actuals!Q25,P$33*P29) -> -264912 | Q21: =IF(Q$13=1,Actuals!R25,Q$33*Q29) -> -154850 | R21: =IF(R$13=1,Actuals!S25,R$33*R29) -> -189180 | S21: =IF(S$13=1,Actuals!T25,S$33*S29) -> -130616 | T21: =IF(T$13=1,Actuals!U25,T$33*T29) -> -229437 | ... BT21: =IF(BT$13=1,Actuals!BU25,BT$33*BT29) -> -149063.19
B22: Ending ARR | F22: $ | G22: =INDEX($M22:$BT22,MATCH(G$8,$M$8:$BT$8,0)) -> 17099065 | H22: =INDEX($M22:$BT22,MATCH(H$8,$M$8:$BT$8,0)) -> 22916197 | I22: =INDEX($M22:$BT22,MATCH(I$8,$M$8:$BT$8,0)) -> 29614278 | J22: =INDEX($M22:$BT22,MATCH(J$8,$M$8:$BT$8,0)) -> 36412072 | K22: =INDEX($M22:$BT22,MATCH(K$8,$M$8:$BT$8,0)) -> 43209783 | M22: =IF(M$13=1,Actuals!N26,sum(M18:M21)) -> 12248800 | N22: =IF(N$13=1,Actuals!O26,sum(N18:N21)) -> 12691380 | O22: =IF(O$13=1,Actuals!P26,sum(O18:O21)) -> 13205436 | P22: =IF(P$13=1,Actuals!Q26,sum(P18:P21)) -> 13595598 | Q22: =IF(Q$13=1,Actuals!R26,sum(Q18:Q21)) -> 13929304 | R22: =IF(R$13=1,Actuals!S26,sum(R18:R21)) -> 14504143 | S22: =IF(S$13=1,Actuals!T26,sum(S18:S21)) -> 15198474 | T22: =IF(T$13=1,Actuals!U26,sum(T18:T21)) -> 15699593 | ... BT22: =IF(BT$13=1,Actuals!BU26,sum(BT18:BT21)) -> 43209783
B24: ='Customer Control'!B23 -> Net new customers | F24: # | G24: ='Customer Control'!F23 -> 148 | H24: ='Customer Control'!G23 -> 146.64575 | I24: ='Customer Control'!H23 -> 158.97737 | J24: ='Customer Control'!I23 -> 162.59793 | K24: ='Customer Control'!J23 -> 162.59507 | M24: ='Customer Control'!L23 -> 9 | N24: ='Customer Control'!M23 -> 10 | O24: ='Customer Control'!N23 -> 12 | P24: ='Customer Control'!O23 -> 12 | Q24: ='Customer Control'!P23 -> 13 | R24: ='Customer Control'!Q23 -> 20 | S24: ='Customer Control'!R23 -> 19 | T24: ='Customer Control'!S23 -> 11 | ... BT24: ='Customer Control'!BS23 -> 13.554067
B26: Customer Summary
B27: Beginning Customers | F27: # | G27: {=INDEX($M27:$BT27,MATCH(G$7,M$7:BH$7,0))} -> 500 | H27: =INDEX($M27:$BH27,MATCH(H$7,N$7:BU$7,0)) -> 638 | I27: =INDEX($M27:$BH27,MATCH(I$7,O$7:BV$7,0)) -> 766.13997 | J27: =INDEX($M27:$BH27,MATCH(J$7,P$7:BW$7,0)) -> 912.91999 | K27: =INDEX($M27:$BH27,MATCH(K$7,Q$7:BX$7,0)) -> 1062.0217 | M27: ='Customer Control'!L18 -> 500 | N27: ='Customer Control'!M18 -> 509 | O27: ='Customer Control'!N18 -> 519 | P27: ='Customer Control'!O18 -> 531 | Q27: ='Customer Control'!P18 -> 543 | R27: ='Customer Control'!Q18 -> 556 | S27: ='Customer Control'!R18 -> 576 | T27: ='Customer Control'!S18 -> 595 | ... BT27: ='Customer Control'!BS18 -> 1265.262
B28: New Customers | F28: # | G28: =SUMIFS($M28:$BT28,$M$15:$BT$15,G$15) -> 248 | H28: =SUMIFS($M28:$BT28,$M$15:$BT$15,H$15) -> 240 | I28: =SUMIFS($M28:$BT28,$M$15:$BT$15,I$15) -> 228 | J28: =SUMIFS($M28:$BT28,$M$15:$BT$15,J$15) -> 228 | K28: =SUMIFS($M28:$BT28,$M$15:$BT$15,K$15) -> 228 | M28: ='Customer Control'!L19 -> 16 | N28: ='Customer Control'!M19 -> 21 | O28: ='Customer Control'!N19 -> 23 | P28: ='Customer Control'!O19 -> 19 | Q28: ='Customer Control'!P19 -> 18 | R28: ='Customer Control'!Q19 -> 28 | S28: ='Customer Control'!R19 -> 25 | T28: ='Customer Control'!S19 -> 23 | ... BT28: ='Customer Control'!BS19 -> 19
B29: Churned Customers | F29: # | G29: =SUMIFS($M29:$BT29,$M$15:$BT$15,G$15) -> -100 | H29: =SUMIFS($M29:$BT29,$M$15:$BT$15,H$15) -> -93.354255 | I29: =SUMIFS($M29:$BT29,$M$15:$BT$15,I$15) -> -69.022628 | J29: =SUMIFS($M29:$BT29,$M$15:$BT$15,J$15) -> -65.40207 | K29: =SUMIFS($M29:$BT29,$M$15:$BT$15,K$15) -> -65.404935 | M29: ='Customer Control'!L20 -> -7 | N29: ='Customer Control'!M20 -> -11 | O29: ='Customer Control'!N20 -> -11 | P29: ='Customer Control'!O20 -> -7 | Q29: ='Customer Control'!P20 -> -5 | R29: ='Customer Control'!Q20 -> -8 | S29: ='Customer Control'!R20 -> -6 | T29: ='Customer Control'!S20 -> -12 | ... BT29: ='Customer Control'!BS20 -> -5.4459327
B30: Ending Customers | F30: # | G30: =INDEX($M30:$BT30,MATCH(G$8,M$8:BT$8,0)) -> 648 | H30: =INDEX($M30:$BT30,MATCH(H$8,N$8:BU$8,0)) -> 780.14179 | I30: =INDEX($M30:$BT30,MATCH(I$8,O$8:BV$8,0)) -> 926.48655 | J30: =INDEX($M30:$BT30,MATCH(J$8,P$8:BW$8,0)) -> 1075.5822 | K30: =INDEX($M30:$BT30,MATCH(K$8,Q$8:BX$8,0)) -> 1224.6219 | M30: ='Customer Control'!L21 -> 509 | N30: ='Customer Control'!M21 -> 519 | O30: ='Customer Control'!N21 -> 531 | P30: ='Customer Control'!O21 -> 543 | Q30: ='Customer Control'!P21 -> 556 | R30: ='Customer Control'!Q21 -> 576 | S30: ='Customer Control'!R21 -> 595 | T30: ='Customer Control'!S21 -> 606 | ... BT30: ='Customer Control'!BS21 -> 1278.8161
B32: Average Contract Value Summary
B33: Forecasted ACV | F33: $ | G33: =iferror(AVERAGEIFS($M33:$BT33,$M$15:$BT$15,G$15),0) -> 25431.513 | H33: =iferror(AVERAGEIFS($M33:$BT33,$M$15:$BT$15,H$15),0) -> 27295.657 | I33: =iferror(AVERAGEIFS($M33:$BT33,$M$15:$BT$15,I$15),0) -> 27371.415 | J33: =iferror(AVERAGEIFS($M33:$BT33,$M$15:$BT$15,J$15),0) -> 27371.471 | K33: =iferror(AVERAGEIFS($M33:$BT33,$M$15:$BT$15,K$15),0) -> 27371.471 | M33: =IF(M13=1,Actuals!N35,AVERAGE(H33:L33)) -> 24064.44 | N33: =IF(N13=1,Actuals!O35,AVERAGE(I33:M33)) -> 24453.525 | O33: =IF(O13=1,Actuals!P35,AVERAGE(J33:N33)) -> 24868.994 | P33: =IF(P13=1,Actuals!Q35,AVERAGE(L33:O33)) -> 25037.935 | Q33: =IF(Q13=1,Actuals!R35,AVERAGE(M33:P33)) -> 25052.705 | R33: =IF(R13=1,Actuals!S35,AVERAGE(N33:Q33)) -> 25180.803 | S33: =IF(S13=1,Actuals!T35,AVERAGE(O33:R33)) -> 25543.654 | T33: =IF(T13=1,Actuals!U35,AVERAGE(P33:S33)) -> 25906.919 | U33: =IF(U13=1,Actuals!V35,AVERAGE(Q33:T33)) -> 26012.974 | V33: =IF(V13=1,Actuals!W35,AVERAGE(R33:U33)) -> 26330.841 | W33: =IF(W13=1,Actuals!X35,AVERAGE(S33:V33)) -> 26337.914 | ... BI33: =IF(BI13=1,Actuals!BJ35,AVERAGE(BE33:BH33)) -> 27371.471 | BJ33: =IF(BJ13=1,Actuals!BW35,AVERAGE(BF33:BI33)) -> 27371.471 | BK33: =IF(BK13=1,Actuals!BX35,AVERAGE(BG33:BJ33)) -> 27371.471 | BL33: =IF(BL13=1,Actuals!BY35,AVERAGE(BH33:BK33)) -> 27371.471 | BM33: =IF(BM13=1,Actuals!BZ35,AVERAGE(BI33:BL33)) -> 27371.471 | BN33: =IF(BN13=1,Actuals!CA35,AVERAGE(BJ33:BM33)) -> 27371.471 | BO33: =IF(BO13=1,Actuals!CB35,AVERAGE(BK33:BN33)) -> 27371.471 | BP33: =IF(BP13=1,Actuals!CC35,AVERAGE(BL33:BO33)) -> 27371.471 | BQ33: =IF(BQ13=1,Actuals!CD35,AVERAGE(BM33:BP33)) -> 27371.471 | ... BT33: =IF(BT13=1,Actuals!CG35,AVERAGE(BP33:BS33)) -> 27371.471
B35: Churn metrics
B36: Customers Available to Renew | F36: # | G36: =SUMIFS($M36:$BT36,$M$15:$BT$15,G$15) -> 395 | H36: =SUMIFS($M36:$BT36,$M$15:$BT$15,H$15) -> 324 | I36: =SUMIFS($M36:$BT36,$M$15:$BT$15,I$15) -> 240 | J36: =SUMIFS($M36:$BT36,$M$15:$BT$15,J$15) -> 228 | K36: =SUMIFS($M36:$BT36,$M$15:$BT$15,K$15) -> 228 | M36: ='Customer Control'!L37 -> 32 | N36: ='Customer Control'!M37 -> 41 | O36: ='Customer Control'!N37 -> 42 | P36: ='Customer Control'!O37 -> 27 | Q36: ='Customer Control'!P37 -> 35 | R36: ='Customer Control'!Q37 -> 34 | S36: ='Customer Control'!R37 -> 39 | T36: ='Customer Control'!S37 -> 33 | ... BT36: ='Customer Control'!BS37 -> 19
B37: ARR Available to Renew | F37: $ | G37: =SUMIFS($M37:$BT37,$M$15:$BT$15,G$15) -> 9915102.5 | H37: =SUMIFS($M37:$BT37,$M$15:$BT$15,H$15) -> 7590986.5 | I37: =SUMIFS($M37:$BT37,$M$15:$BT$15,I$15) -> 5764112.4 | J37: =SUMIFS($M37:$BT37,$M$15:$BT$15,J$15) -> 6240682.6 | K37: =SUMIFS($M37:$BT37,$M$15:$BT$15,K$15) -> 6240695.3 | M37: =if(M$13=1,Actuals!N72,A19) -> 760857.5 | N37: =if(N$13=1,Actuals!O72,B19) -> 738900 | O37: =if(O$13=1,Actuals!P72,C19) -> 993687.5 | P37: =if(P$13=1,Actuals!Q72,D19) -> 852650 | Q37: =if(Q$13=1,Actuals!R72,E19) -> 635907.5 | R37: =if(R$13=1,Actuals!S72,F19) -> 994452.5 | S37: =if(S$13=1,Actuals!T72,G19) -> 1073757.5 | T37: =if(T$13=1,Actuals!U72,H19) -> 950895 | ... BT37: =if(BT$13=1,Actuals!BU72,BH19) -> 520057.94
B38: % Customer Churn | F38: % | G38: =iferror(AVERAGEIFS($M38:$BT38,$M$15:$BT$15,G$15),0) -> 0.25612251 | H38: =iferror(AVERAGEIFS($M38:$BT38,$M$15:$BT$15,H$15),0) -> 0.28838415 | I38: =iferror(AVERAGEIFS($M38:$BT38,$M$15:$BT$15,I$15),0) -> 0.28724948 | J38: =iferror(AVERAGEIFS($M38:$BT38,$M$15:$BT$15,J$15),0) -> 0.28685119 | K38: =iferror(AVERAGEIFS($M38:$BT38,$M$15:$BT$15,K$15),0) -> 0.28686375 | M38: ='Customer Control'!L38 -> 0.21875 | N38: ='Customer Control'!M38 -> 0.26829268 | O38: ='Customer Control'!N38 -> 0.26190476 | P38: ='Customer Control'!O38 -> 0.25925926 | Q38: ='Customer Control'!P38 -> 0.14285714 | R38: ='Customer Control'!Q38 -> 0.23529412 | S38: ='Customer Control'!R38 -> 0.15384615 | T38: ='Customer Control'!S38 -> 0.36363636 | ... BT38: ='Customer Control'!BS38 -> 0.28662804
B39: % ARR Churn | F39: % | G39: =iferror(AVERAGEIFS($M39:$BT39,$M$15:$BT$15,G$15),0) -> 0.25513059 | H39: =iferror(AVERAGEIFS($M39:$BT39,$M$15:$BT$15,H$15),0) -> 0.32341092 | I39: =iferror(AVERAGEIFS($M39:$BT39,$M$15:$BT$15,I$15),0) -> 0.33045508 | J39: =iferror(AVERAGEIFS($M39:$BT39,$M$15:$BT$15,J$15),0) -> 0.28685177 | K39: =iferror(AVERAGEIFS($M39:$BT39,$M$15:$BT$15,K$15),0) -> 0.28686375 | M39: =-M21/M37 -> 0.35585113 | N39: =-N21/N37 -> 0.16931114 | O39: =-O21/O37 -> 0.25095918 | P39: =-P21/P37 -> 0.31069255 | Q39: =-Q21/Q37 -> 0.24351026 | R39: =-R21/R37 -> 0.19023533 | S39: =-S21/S37 -> 0.12164385 | T39: =-T21/T37 -> 0.24128532 | ... BT39: =-BT21/BT37 -> 0.28662804
B41: Customer Retention | F41: % | G41: =(G36+G29)/G36 -> 0.74683544 | H41: =(H36+H29)/H36 -> 0.71186958 | I41: =(I36+I29)/I36 -> 0.71240572 | J41: =(J36+J29)/J36 -> 0.71314881 | K41: =(K36+K29)/K36 -> 0.71313625 | M41: =(M36+M29)/M36 -> 0.78125 | N41: =(N36+N29)/N36 -> 0.73170732 | O41: =(O36+O29)/O36 -> 0.73809524 | P41: =(P36+P29)/P36 -> 0.74074074 | Q41: =(Q36+Q29)/Q36 -> 0.85714286 | R41: =(R36+R29)/R36 -> 0.76470588 | S41: =(S36+S29)/S36 -> 0.84615385 | T41: =(T36+T29)/T36 -> 0.63636364 | ... BT41: =(BT36+BT29)/BT36 -> 0.71337196
B42: Gross Dollar Retention (GRR) | F42: % | G42: =Actuals!H74 -> 0.7366 | H42: =Actuals!I74 -> 0.7465 | I42: 0.8729 | J42: 0.89 | K42: 0.9 | M42: =Actuals!N74 -> 0.77416089 | N42: =Actuals!O74 -> 0.71439002 | O42: =Actuals!P74 -> 0.6465856 | P42: =Actuals!Q74 -> 0.72688936 | Q42: =Actuals!R74 -> 0.63821734 | R42: =Actuals!S74 -> 0.86334371 | S42: =Actuals!T74 -> 0.7727358 | T42: =Actuals!U74 -> 0.67358338 | ... AD42: =Actuals!AE74 -> 0.76515322 | AE42: 0.77986378 | AF42: 0.84236257 | AG42: 0.92487303 | AH42: 0.82939275 | AI42: 0.9791076 | AJ42: 0.96 | AK42: 0.83393937 | AL42: 0.873746 | AM42: 0.91 | AN42: 0.87297428 | AO42: 0.76557584 | AP42: 0.83771781 | AQ42: 0.88674301 | AR42: 0.88559028 | AS42: 0.88803397 | AT42: 0.89030993 | AU42: 0.88868364 | AV42: 0.89169824 | AW42: 0.89154911 | AX42: 0.88905633 | AY42: 0.88805567 | AZ42: 0.88850517 | BA42: 0.887865 | BB42: 0.88884184 | BC42: 0.89003246 | BD42: 0.89025082 | BE42: 0.88982747 | BF42: 0.88978342 | BG42: 0.88900029 | BH42: 0.88845952 | BI42: 0.88865839 | BJ42: 0.88910044 | BK42: 0.88936629 | BL42: 0.88974748 | BM42: 0.88977758 | BN42: 0.88946366 | BO42: 0.88914592 | BP42: 0.88900085 | BQ42: 0.88891727 | BR42: 0.88906628 | BS42: 0.88932982 | BT42: 0.88949106
B43: Net Dollar Retention (NRR) | F43: % | G43: =(G37+G21+G20+G19)/G37 -> 1.5208282 | H43: =(H37+H21+H20+H19)/H37 -> 1.7663209 | I43: 1.2 | J43: 1.15 | K43: 1.21 | M43: =Actuals!N75 -> 1.1029474 | N43: =Actuals!O75 -> 1.1537521 | O43: =Actuals!P75 -> 1.2498159 | P43: =Actuals!Q75 -> 1.0214469 | Q43: =Actuals!R75 -> 1.0383119 | R43: =Actuals!S75 -> 1.0357644 | S43: =Actuals!T75 -> 1.1883622 | T43: =Actuals!U75 -> 1.0136102 | ... AD43: =Actuals!AE75 -> 1.1427854 | AE43: 1.0877634 | AF43: 1.2681977 | AG43: 1.33 | AH43: 1.1469548 | AI43: 1.34 | AJ43: 1.35 | AK43: 1.36 | AL43: 1.2956552 | AM43: 1.33 | AN43: 1.37 | AO43: 1.2041079 | AP43: 1.19 | AQ43: 1.07 | AR43: 1.11 | AS43: 1.09 | AT43: 1.08 | AU43: 1.15 | AV43: 1.13 | AW43: 1.17 | AX43: 1.195 | AY43: 1.06 | AZ43: 1.245 | BA43: 1.1 | BB43: 1.13 | BC43: 1.12 | BD43: 1.345 | BE43: 1.03 | BF43: 1.19 | BG43: 1.18 | BH43: 1.045 | BI43: 1.07 | BJ43: 1.095 | BK43: 1.12 | BL43: 1.145 | BM43: 1.17 | BN43: 1.195 | BO43: 1.22 | BP43: 1.245 | BQ43: 1.27 | BR43: 1.295 | BS43: 1.32 | BT43: 1.345
B45: SaaS Metrics
B46: Average Lifetime (in years) | F46: # | G46: =iferror(1/G38,0) -> 3.9043816 | H46: =iferror(1/H38,0) -> 3.4675969 | I46: =iferror(1/I38,0) -> 3.4812944 | J46: =iferror(1/J38,0) -> 3.4861282 | K46: =iferror(1/K38,0) -> 3.4859755 | M46: =if(M13=1,Actuals!N77, 1/M38) -> 4.5714286 | N46: =if(N13=1,Actuals!O77, 1/N38) -> 3.7272727 | O46: =if(O13=1,Actuals!P77, 1/O38) -> 3.8181818 | P46: =if(P13=1,Actuals!Q77, 1/P38) -> 3.8571429 | Q46: =if(Q13=1,Actuals!R77, 1/Q38) -> 7 | R46: =if(R13=1,Actuals!S77, 1/R38) -> 4.25 | S46: =if(S13=1,Actuals!T77, 1/S38) -> 6.5 | T46: =if(T13=1,Actuals!U77, 1/T38) -> 2.75 | ... BT46: =if(BT13=1,Actuals!BU77, 1/BT38) -> 3.4888422
B47: LTV | F47: $ | G47: =SUMIFS($M47:$BT47,$M$15:$BT$15,G$15) -> 1021595.8 | H47: =SUMIFS($M47:$BT47,$M$15:$BT$15,H$15) -> 1010950.2 | I47: =SUMIFS($M47:$BT47,$M$15:$BT$15,I$15) -> 1140714.3 | J47: =SUMIFS($M47:$BT47,$M$15:$BT$15,J$15) -> 1145057.5 | K47: =SUMIFS($M47:$BT47,$M$15:$BT$15,K$15) -> 1144996.7 | M47: =if(M13=1,Actuals!N78,M46*A33) -> 88007.096 | N47: =if(N13=1,Actuals!O78,N46*B33) -> 72915.966 | O47: =if(O13=1,Actuals!P78,O46*C33) -> 75963.473 | P47: =if(P13=1,Actuals!Q78,P46*D33) -> 77259.912 | Q47: =if(Q13=1,Actuals!R78,Q46*E33) -> 140295.15 | R47: =if(R13=1,Actuals!S78,R46*F33) -> 85614.731 | S47: =if(S13=1,Actuals!T78,S46*G33) -> 132827 | T47: =if(T13=1,Actuals!U78,T46*H33) -> 56995.221 | ... BT47: =if(BT13=1,Actuals!BU78,BT46*BH33) -> 95494.743
B48: CAC | F48: $ | G48: =SUMIFS($M48:$BT48,$M$15:$BT$15,G$15) -> 359046.22 | H48: =SUMIFS($M48:$BT48,$M$15:$BT$15,H$15) -> 369780.86 | I48: =SUMIFS($M48:$BT48,$M$15:$BT$15,I$15) -> 382869.97 | J48: =SUMIFS($M48:$BT48,$M$15:$BT$15,J$15) -> 390289.41 | K48: =SUMIFS($M48:$BT48,$M$15:$BT$15,K$15) -> 394998.73 | M48: =if(M13=1,Actuals!N79,'P&L'!A28*1000) -> 37500 | N48: =if(N13=1,Actuals!O79,'P&L'!B28*1000) -> 28571.429 | O48: =if(O13=1,Actuals!P79,'P&L'!C28*1000) -> 26086.957 | P48: =if(P13=1,Actuals!Q79,'P&L'!D28*1000) -> 31578.947 | Q48: =if(Q13=1,Actuals!R79,'P&L'!E28*1000) -> 33333.333 | R48: =if(R13=1,Actuals!S79,'P&L'!F28*1000) -> 21428.571 | S48: =if(S13=1,Actuals!T79,'P&L'!G28*1000) -> 24000 | T48: =if(T13=1,Actuals!U79,'P&L'!H28*1000) -> 26086.957 | ... AD48: =if(AD13=1,Actuals!AE79,'P&L'!R28*1000) -> 26086.957 | AE48: =if(AE13=1,Actuals!AF79,'P&L'!S28*1000/AE28) -> 31578.947 | AF48: =if(AF13=1,Actuals!AG79,'P&L'!T28*1000/AF28) -> 31578.947 | AG48: =if(AG13=1,Actuals!AH79,'P&L'!U28*1000/AG28) -> 31578.947 | AH48: =if(AH13=1,Actuals!AI79,'P&L'!V28*1000/AH28) -> 31578.947 | AI48: =if(AI13=1,Actuals!AJ79,'P&L'!W28*1000/AI28) -> 31578.947 | AJ48: =if(AJ13=1,Actuals!AK79,'P&L'!X28*1000/AJ28) -> 31578.947 | AK48: =if(AK13=1,Actuals!AL79,'P&L'!Y28*1000/AK28) -> 31578.947 | AL48: =if(AL13=1,Actuals!AM79,'P&L'!Z28*1000/AL28) -> 31578.947 | ... BT48: =if(BT13=1,Actuals!BU79,'P&L'!BH28*1000/BT28) -> 33097.812
B49: LTV:CAC | F49: # | G49: =G47/G48 -> 2.8453044 | H49: =H47/H48 -> 2.7339169 | I49: =I47/I48 -> 2.9793779 | J49: =J47/J48 -> 2.9338677 | K49: =K47/K48 -> 2.8987353 | M49: =M47/M48 -> 2.3468559 | N49: =N47/N48 -> 2.5520588 | O49: =O47/O48 -> 2.9119331 | P49: =P47/P48 -> 2.4465639 | Q49: =Q47/Q48 -> 4.2088544 | R49: =R47/R48 -> 3.9953541 | S49: =S47/S48 -> 5.5344584 | T49: =T47/T48 -> 2.1848168 | ... BT49: =BT47/BT48 -> 2.8852282
B50: Rule of 40 | F50: % | G50: =IFERROR('P&L'!G33+'P&L'!G20,0) -> 0 | H50: =IFERROR('P&L'!H33+'P&L'!H20,0) -> 0.42043741 | I50: =IFERROR('P&L'!I33+'P&L'!I20,0) -> 0.53908644 | J50: =IFERROR('P&L'!J33+'P&L'!J20,0) -> 0.58552753 | K50: =IFERROR('P&L'!K33+'P&L'!K20,0) -> 0.60947923 | M50: =IFERROR('P&L'!M33+'P&L'!M20,0) -> 0 | N50: =IFERROR('P&L'!N33+'P&L'!N20,0) -> -0.34577212 | O50: =IFERROR('P&L'!O33+'P&L'!O20,0) -> -0.29539151 | P50: =IFERROR('P&L'!P33+'P&L'!P20,0) -> -0.27375264 | Q50: =IFERROR('P&L'!Q33+'P&L'!Q20,0) -> -0.25232136 | R50: =IFERROR('P&L'!R33+'P&L'!R20,0) -> -0.19291897 | S50: =IFERROR('P&L'!S33+'P&L'!S20,0) -> -0.13906992 | T50: =IFERROR('P&L'!T33+'P&L'!T20,0) -> -0.12246717 | ... BT50: =IFERROR('P&L'!BT33+'P&L'!BT20,0) -> 0.44505648

Sheet P&L
B2: Income statement (P&L) SaaS Financial Model
G5: =IF(G13=1,"Actual","Forecast") -> Actual | H5: =IF(H13=1,"Actual","Forecast") -> Actual | I5: =IF(I13=1,"Actual","Forecast") -> Forecast | J5: =IF(J13=1,"Actual","Forecast") -> Forecast | K5: =IF(K13=1,"Actual","Forecast") -> Forecast | M5: =IF(M13=1,"Actual","Forecast") -> Actual | N5: =IF(N13=1,"Actual","Forecast") -> Actual | O5: =IF(O13=1,"Actual","Forecast") -> Actual | P5: =IF(P13=1,"Actual","Forecast") -> Actual | Q5: =IF(Q13=1,"Actual","Forecast") -> Actual | R5: =IF(R13=1,"Actual","Forecast") -> Actual | S5: =IF(S13=1,"Actual","Forecast") -> Actual | T5: =IF(T13=1,"Actual","Forecast") -> Actual | ... BT5: =IF(BT13=1,"Actual","Forecast") -> Forecast
G6: =G7 -> 44562 | H6: =H7 -> 44927 | I6: =I7 -> 45292 | J6: =J7 -> 45658 | K6: =K7 -> 46023 | M6: =M7 -> 44562 | N6: =N7 -> 44593 | O6: =O7 -> 44621 | P6: =P7 -> 44652 | Q6: =Q7 -> 44682 | R6: =R7 -> 44713 | S6: =S7 -> 44743 | T6: =T7 -> 44774 | ... BT6: =BT7 -> 46357
F7: Start Date | G7: ='Key Assumptions'!D13 -> 44562 | H7: =G8+1 -> 44927 | I7: =H8+1 -> 45292 | J7: =I8+1 -> 45658 | K7: =J8+1 -> 46023 | M7: ='Key Assumptions'!D13 -> 44562 | N7: =M8+1 -> 44593 | O7: =N8+1 -> 44621 | P7: =O8+1 -> 44652 | Q7: =P8+1 -> 44682 | R7: =Q8+1 -> 44713 | S7: =R8+1 -> 44743 | T7: =S8+1 -> 44774 | U7: =T8+1 -> 44805 | ... BT7: =BS8+1 -> 46357
F8: End Date | G8: =EOMONTH(G7,11) -> 44926 | H8: =EOMONTH(H7,11) -> 45291 | I8: =EOMONTH(I7,11) -> 45657 | J8: =EOMONTH(J7,11) -> 46022 | K8: =EOMONTH(K7,11) -> 46387 | M8: =EOMONTH(M7,0) -> 44592 | N8: =EOMONTH(N7,0) -> 44620 | O8: =EOMONTH(O7,0) -> 44651 | P8: =EOMONTH(P7,0) -> 44681 | Q8: =EOMONTH(Q7,0) -> 44712 | R8: =EOMONTH(R7,0) -> 44742 | S8: =EOMONTH(S7,0) -> 44773 | T8: =EOMONTH(T7,0) -> 44804 | ... BT8: =EOMONTH(BT7,0) -> 46387
F9: Timeline | G9: =IF(G8-G7>35,"Annual","Monthly") -> Annual | H9: =IF(H8-H7>35,"Annual","Monthly") -> Annual | I9: =IF(I8-I7>35,"Annual","Monthly") -> Annual | J9: =IF(J8-J7>35,"Annual","Monthly") -> Annual | K9: =IF(K8-K7>35,"Annual","Monthly") -> Annual | M9: =IF(M8-M7>35,"Annual","Monthly") -> Monthly | N9: =IF(N8-N7>35,"Annual","Monthly") -> Monthly | O9: =IF(O8-O7>35,"Annual","Monthly") -> Monthly | P9: =IF(P8-P7>35,"Annual","Monthly") -> Monthly | Q9: =IF(Q8-Q7>35,"Annual","Monthly") -> Monthly | R9: =IF(R8-R7>35,"Annual","Monthly") -> Monthly | S9: =IF(S8-S7>35,"Annual","Monthly") -> Monthly | T9: =IF(T8-T7>35,"Annual","Monthly") -> Monthly | ... BT9: =IF(BT8-BT7>35,"Annual","Monthly") -> Monthly
F10: Year | G10: =YEAR(G7) -> 2022 | H10: =YEAR(H7) -> 2023 | I10: =YEAR(I7) -> 2024 | J10: =YEAR(J7) -> 2025 | K10: =YEAR(K7) -> 2026 | M10: =YEAR(M7) -> 2022 | N10: =YEAR(N7) -> 2022 | O10: =YEAR(O7) -> 2022 | P10: =YEAR(P7) -> 2022 | Q10: =YEAR(Q7) -> 2022 | R10: =YEAR(R7) -> 2022 | S10: =YEAR(S7) -> 2022 | T10: =YEAR(T7) -> 2022 | ... BT10: =YEAR(BT7) -> 2026
F12: Flag
F13: Historical Flag | G13: =IF(AND(G7>='Key Assumptions'!$D$13,G7<'Key Assumptions'!$D$14),1,0) -> 1 | H13: =IF(AND(H7>='Key Assumptions'!$D$13,H7<'Key Assumptions'!$D$14),1,0) -> 1 | I13: =IF(AND(I7>='Key Assumptions'!$D$13,I7<'Key Assumptions'!$D$14),1,0) -> 0 | J13: =IF(AND(J7>='Key Assumptions'!$D$13,J7<'Key Assumptions'!$D$14),1,0) -> 0 | K13: =IF(AND(K7>='Key Assumptions'!$D$13,K7<'Key Assumptions'!$D$14),1,0) -> 0 | M13: =IF(AND(M7>='Key Assumptions'!$D$13,M7<'Key Assumptions'!$D$14),1,0) -> 1 | N13: =IF(AND(N7>='Key Assumptions'!$D$13,N7<'Key Assumptions'!$D$14),1,0) -> 1 | O13: =IF(AND(O7>='Key Assumptions'!$D$13,O7<'Key Assumptions'!$D$14),1,0) -> 1 | P13: =IF(AND(P7>='Key Assumptions'!$D$13,P7<'Key Assumptions'!$D$14),1,0) -> 1 | Q13: =IF(AND(Q7>='Key Assumptions'!$D$13,Q7<'Key Assumptions'!$D$14),1,0) -> 1 | R13: =IF(AND(R7>='Key Assumptions'!$D$13,R7<'Key Assumptions'!$D$14),1,0) -> 1 | S13: =IF(AND(S7>='Key Assumptions'!$D$13,S7<'Key Assumptions'!$D$14),1,0) -> 1 | T13: =IF(AND(T7>='Key Assumptions'!$D$13,T7<'Key Assumptions'!$D$14),1,0) -> 1 | ... BT13: =IF(AND(BT7>='Key Assumptions'!$D$13,BT7<'Key Assumptions'!$D$14),1,0) -> 0
F14: Forecast Flag | G14: =IF(AND(G7>='Key Assumptions'!$D$15,G7<'Key Assumptions'!$D$16),1,0) -> 0 | H14: =IF(AND(H7>='Key Assumptions'!$D$15,H7<'Key Assumptions'!$D$16),1,0) -> 0 | I14: =IF(AND(I7>='Key Assumptions'!$D$15,I7<'Key Assumptions'!$D$16),1,0) -> 1 | J14: =IF(AND(J7>='Key Assumptions'!$D$15,J7<'Key Assumptions'!$D$16),1,0) -> 1 | K14: =IF(AND(K7>='Key Assumptions'!$D$15,K7<'Key Assumptions'!$D$16),1,0) -> 1 | M14: =IF(AND(M7>='Key Assumptions'!$D$15,M7<'Key Assumptions'!$D$16),1,0) -> 0 | N14: =IF(AND(N7>='Key Assumptions'!$D$15,N7<'Key Assumptions'!$D$16),1,0) -> 0 | O14: =IF(AND(O7>='Key Assumptions'!$D$15,O7<'Key Assumptions'!$D$16),1,0) -> 0 | P14: =IF(AND(P7>='Key Assumptions'!$D$15,P7<'Key Assumptions'!$D$16),1,0) -> 0 | Q14: =IF(AND(Q7>='Key Assumptions'!$D$15,Q7<'Key Assumptions'!$D$16),1,0) -> 0 | R14: =IF(AND(R7>='Key Assumptions'!$D$15,R7<'Key Assumptions'!$D$16),1,0) -> 0 | S14: =IF(AND(S7>='Key Assumptions'!$D$15,S7<'Key Assumptions'!$D$16),1,0) -> 0 | T14: =IF(AND(T7>='Key Assumptions'!$D$15,T7<'Key Assumptions'!$D$16),1,0) -> 0 | ... BT14: =IF(AND(BT7>='Key Assumptions'!$D$15,BT7<'Key Assumptions'!$D$16),1,0) -> 1
F15: Year Flag | G15: =COUNTA($G$7:G7) -> 1 | H15: =COUNTA($G$7:H7) -> 2 | I15: =COUNTA($G$7:I7) -> 3 | J15: =COUNTA($G$7:J7) -> 4 | K15: =COUNTA($G$7:K7) -> 5 | M15: =INDEX($G$15:$K$15,MATCH(YEAR(M$7),$G$10:$K$10,0)) -> 1 | N15: =INDEX($G$15:$K$15,MATCH(YEAR(N$7),$G$10:$K$10,0)) -> 1 | O15: =INDEX($G$15:$K$15,MATCH(YEAR(O$7),$G$10:$K$10,0)) -> 1 | P15: =INDEX($G$15:$K$15,MATCH(YEAR(P$7),$G$10:$K$10,0)) -> 1 | Q15: =INDEX($G$15:$K$15,MATCH(YEAR(Q$7),$G$10:$K$10,0)) -> 1 | R15: =INDEX($G$15:$K$15,MATCH(YEAR(R$7),$G$10:$K$10,0)) -> 1 | S15: =INDEX($G$15:$K$15,MATCH(YEAR(S$7),$G$10:$K$10,0)) -> 1 | T15: =INDEX($G$15:$K$15,MATCH(YEAR(T$7),$G$10:$K$10,0)) -> 1 | ... BT15: =INDEX($G$15:$K$15,MATCH(YEAR(BT$7),$G$10:$K$10,0)) -> 5
B17: P&L
B19: Revenue | F19: $'000s | G19: =SUMIFS($M19:$BT19,$M$15:$BT$15,G$15) -> 14794.622 | H19: =SUMIFS($M19:$BT19,$M$15:$BT$15,H$15) -> 20075.879 | I19: =SUMIFS($M19:$BT19,$M$15:$BT$15,I$15) -> 26528.89 | J19: =SUMIFS($M19:$BT19,$M$15:$BT$15,J$15) -> 33296.577 | K19: =SUMIFS($M19:$BT19,$M$15:$BT$15,K$15) -> 40094.115 | M19: =if(M11=10,Actuals!N54,Summary!M22/12/1000) -> 1020.7333 | N19: =if(N11=10,Actuals!O54,Summary!N22/12/1000) -> 1057.615 | O19: =if(O11=10,Actuals!P54,Summary!O22/12/1000) -> 1100.453 | P19: =if(P11=10,Actuals!Q54,Summary!P22/12/1000) -> 1132.9665 | Q19: =if(Q11=10,Actuals!R54,Summary!Q22/12/1000) -> 1160.7753 | R19: =if(R11=10,Actuals!S54,Summary!R22/12/1000) -> 1208.6786 | S19: =if(S11=10,Actuals!T54,Summary!S22/12/1000) -> 1266.5395 | T19: =if(T11=10,Actuals!U54,Summary!T22/12/1000) -> 1308.2994 | ... BT19: =if(BT11=10,Actuals!BU54,Summary!BT22/12/1000) -> 3600.8153
B20: Revenue Growth | F20: % | G20: =IFERROR(G19/F19-1,"na") -> na | H20: =IFERROR(H19/G19-1,0) -> 0.35697143 | I20: =IFERROR(I19/H19-1,0) -> 0.32143105 | J20: =IFERROR(J19/I19-1,0) -> 0.25510631 | K20: =IFERROR(K19/J19-1,0) -> 0.20415127 | M20: =IFERROR(M19/L19-1,"na") -> na | N20: =IFERROR(N19/M19-1,0) -> 0.03613248 | O20: =IFERROR(O19/N19-1,0) -> 0.040504359 | P20: =IFERROR(P19/O19-1,0) -> 0.029545608 | Q20: =IFERROR(Q19/P19-1,0) -> 0.024545097 | R20: =IFERROR(R19/Q19-1,0) -> 0.041268318 | S20: =IFERROR(S19/R19-1,0) -> 0.047871256 | T20: =IFERROR(T19/S19-1,0) -> 0.032971629 | U20: =IFERROR(U19/T19-1,0) -> 0.01900601 | ... BT20: =IFERROR(BT19/BS19-1,0) -> 0.013286964
B22: COGS | F22: $'000s | G22: =SUMIFS($M22:$BT22,$M$15:$BT$15,G$15) -> -2654.7948 | H22: =SUMIFS($M22:$BT22,$M$15:$BT$15,H$15) -> -3646.4742 | I22: =SUMIFS($M22:$BT22,$M$15:$BT$15,I$15) -> -5305.7779 | J22: =SUMIFS($M22:$BT22,$M$15:$BT$15,J$15) -> -6659.3154 | K22: =SUMIFS($M22:$BT22,$M$15:$BT$15,K$15) -> -8018.8231 | M22: =if(M13=1,Actuals!N57,-(M19-M23)) -> -199.50063 | N22: =if(N13=1,Actuals!O57,-(N19-N23)) -> -203.98357 | O22: =if(O13=1,Actuals!P57,-(O19-O23)) -> -208.66008 | P22: =if(P13=1,Actuals!Q57,-(P19-P23)) -> -211.82398 | Q22: =if(Q13=1,Actuals!R57,-(Q19-Q23)) -> -214.89565 | R22: =if(R13=1,Actuals!S57,-(R19-R23)) -> -220.58222 | S22: =if(S13=1,Actuals!T57,-(S19-S23)) -> -227.94978 | T22: =if(T13=1,Actuals!U57,-(T19-T23)) -> -232.57823 | ... BT22: =if(BT13=1,Actuals!BU57,-(BT19-BT23)) -> -720.16306
B23: Gross Profit | F23: $'000s | G23: =G19+G22 -> 12139.827 | H23: =H19+H22 -> 16429.405 | I23: =I19+I22 -> 21223.112 | J23: =J19+J22 -> 26637.262 | K23: =K19+K22 -> 32075.292 | M23: =M19*M24 -> 816.58667 | N23: =N19*N24 -> 846.09198 | O23: =O19*O24 -> 880.36239 | P23: =P19*P24 -> 906.37323 | Q23: =Q19*Q24 -> 928.62025 | R23: =R19*R24 -> 966.94285 | S23: =S19*S24 -> 1013.2316 | T23: =T19*T24 -> 1046.6395 | ... BT23: =BT19*BT24 -> 2880.6522
B24: Gross Margin | F24: % | G24: =AVERAGEIFS($M24:$BT24,$M$15:$BT$15,G$15) -> 0.8 | H24: =AVERAGEIFS($M24:$BT24,$M$15:$BT$15,H$15) -> 0.8 | I24: =AVERAGEIFS($M24:$BT24,$M$15:$BT$15,I$15) -> 0.8 | J24: =AVERAGEIFS($M24:$BT24,$M$15:$BT$15,J$15) -> 0.8 | K24: =AVERAGEIFS($M24:$BT24,$M$15:$BT$15,K$15) -> 0.8 | M24: ='Key Assumptions'!O32 -> 0.8 | N24: ='Key Assumptions'!P32 -> 0.8 | O24: ='Key Assumptions'!Q32 -> 0.8 | P24: ='Key Assumptions'!R32 -> 0.8 | Q24: ='Key Assumptions'!S32 -> 0.8 | R24: ='Key Assumptions'!T32 -> 0.8 | S24: ='Key Assumptions'!U32 -> 0.8 | T24: ='Key Assumptions'!V32 -> 0.8 | ... BT24: ='Key Assumptions'!BV32 -> 0.8
B26: Operating Expenses
B27: ='Key Assumptions'!C33 -> G&A | F27: $'000s | G27: =SUMIFS($M27:$BT27,$M$15:$BT$15,G$15) -> 3000 | H27: =SUMIFS($M27:$BT27,$M$15:$BT$15,H$15) -> 3031.0539 | I27: =SUMIFS($M27:$BT27,$M$15:$BT$15,I$15) -> 3089.7912 | J27: =SUMIFS($M27:$BT27,$M$15:$BT$15,J$15) -> 3127.0733 | K27: =SUMIFS($M27:$BT27,$M$15:$BT$15,K$15) -> 3164.8052 | M27: =if(M$13=1,Actuals!N62,'Key Assumptions'!O33/1000) -> 250 | N27: =if(N$13=1,Actuals!O62,'Key Assumptions'!P33/1000) -> 250 | O27: =if(O$13=1,Actuals!P62,'Key Assumptions'!Q33/1000) -> 250 | P27: =if(P$13=1,Actuals!Q62,'Key Assumptions'!R33/1000) -> 250 | Q27: =if(Q$13=1,Actuals!R62,'Key Assumptions'!S33/1000) -> 250 | R27: =if(R$13=1,Actuals!S62,'Key Assumptions'!T33/1000) -> 250 | S27: =if(S$13=1,Actuals!T62,'Key Assumptions'!U33/1000) -> 250 | T27: =if(T$13=1,Actuals!U62,'Key Assumptions'!V33/1000) -> 250 | ... AD27: =if(AD$13=1,Actuals!AE62,'Key Assumptions'!AF33/1000) -> 250 | AE27: =if(AE$13=1,Actuals!AF62,'Key Assumptions'!AG33) -> 254.53845 | AF27: =if(AF$13=1,Actuals!AG62,'Key Assumptions'!AH33) -> 254.79299 | AG27: =if(AG$13=1,Actuals!AH62,'Key Assumptions'!AI33) -> 255.04779 | AH27: =if(AH$13=1,Actuals!AI62,'Key Assumptions'!AJ33) -> 255.30283 | AI27: =if(AI$13=1,Actuals!AJ62,'Key Assumptions'!AK33) -> 255.55814 | AJ27: =if(AJ$13=1,Actuals!AK62,'Key Assumptions'!AL33) -> 255.81369 | AK27: =if(AK$13=1,Actuals!AL62,'Key Assumptions'!AM33) -> 256.06951 | AL27: =if(AL$13=1,Actuals!AM62,'Key Assumptions'!AN33) -> 256.32558 | ... BT27: =if(BT$13=1,Actuals!BU62,'Key Assumptions'!BV33) -> 265.18599
B28: ='Key Assumptions'!C34 -> S&M | F28: $'000s | G28: =SUMIFS($M28:$BT28,$M$15:$BT$15,G$15) -> 7200 | H28: =SUMIFS($M28:$BT28,$M$15:$BT$15,H$15) -> 7274.5294 | I28: =SUMIFS($M28:$BT28,$M$15:$BT$15,I$15) -> 7415.4988 | J28: =SUMIFS($M28:$BT28,$M$15:$BT$15,J$15) -> 7504.9758 | K28: =SUMIFS($M28:$BT28,$M$15:$BT$15,K$15) -> 7595.5325 | M28: =if(M$13=1,Actuals!N63,'Key Assumptions'!O34/1000) -> 600 | N28: =if(N$13=1,Actuals!O63,'Key Assumptions'!P34/1000) -> 600 | O28: =if(O$13=1,Actuals!P63,'Key Assumptions'!Q34/1000) -> 600 | P28: =if(P$13=1,Actuals!Q63,'Key Assumptions'!R34/1000) -> 600 | Q28: =if(Q$13=1,Actuals!R63,'Key Assumptions'!S34/1000) -> 600 | R28: =if(R$13=1,Actuals!S63,'Key Assumptions'!T34/1000) -> 600 | S28: =if(S$13=1,Actuals!T63,'Key Assumptions'!U34/1000) -> 600 | T28: =if(T$13=1,Actuals!U63,'Key Assumptions'!V34/1000) -> 600 | ... AD28: =if(AD$13=1,Actuals!AE63,'Key Assumptions'!AF34/1000) -> 600 | AE28: =if(AE$13=1,Actuals!AF63,'Key Assumptions'!AG34) -> 610.89229 | AF28: =if(AF$13=1,Actuals!AG63,'Key Assumptions'!AH34) -> 611.50318 | AG28: =if(AG$13=1,Actuals!AH63,'Key Assumptions'!AI34) -> 612.11469 | AH28: =if(AH$13=1,Actuals!AI63,'Key Assumptions'!AJ34) -> 612.7268 | AI28: =if(AI$13=1,Actuals!AJ63,'Key Assumptions'!AK34) -> 613.33953 | AJ28: =if(AJ$13=1,Actuals!AK63,'Key Assumptions'!AL34) -> 613.95287 | AK28: =if(AK$13=1,Actuals!AL63,'Key Assumptions'!AM34) -> 614.56682 | AL28: =if(AL$13=1,Actuals!AM63,'Key Assumptions'!AN34) -> 615.18139 | ... BT28: =if(BT$13=1,Actuals!BU63,'Key Assumptions'!BV34) -> 636.44638
B29: ='Key Assumptions'!C35 -> R&D | F29: $'000s | G29: =SUMIFS($M29:$BT29,$M$15:$BT$15,G$15) -> 4800 | H29: =SUMIFS($M29:$BT29,$M$15:$BT$15,H$15) -> 4849.6862 | I29: =SUMIFS($M29:$BT29,$M$15:$BT$15,I$15) -> 4943.6658 | J29: =SUMIFS($M29:$BT29,$M$15:$BT$15,J$15) -> 5003.3172 | K29: =SUMIFS($M29:$BT29,$M$15:$BT$15,K$15) -> 5063.6883 | M29: =if(M$13=1,Actuals!N64,'Key Assumptions'!O35/1000) -> 400 | N29: =if(N$13=1,Actuals!O64,'Key Assumptions'!P35/1000) -> 400 | O29: =if(O$13=1,Actuals!P64,'Key Assumptions'!Q35/1000) -> 400 | P29: =if(P$13=1,Actuals!Q64,'Key Assumptions'!R35/1000) -> 400 | Q29: =if(Q$13=1,Actuals!R64,'Key Assumptions'!S35/1000) -> 400 | R29: =if(R$13=1,Actuals!S64,'Key Assumptions'!T35/1000) -> 400 | S29: =if(S$13=1,Actuals!T64,'Key Assumptions'!U35/1000) -> 400 | T29: =if(T$13=1,Actuals!U64,'Key Assumptions'!V35/1000) -> 400 | ... AD29: =if(AD$13=1,Actuals!AE64,'Key Assumptions'!AF35/1000) -> 400 | AE29: =if(AE$13=1,Actuals!AF64,'Key Assumptions'!AG35) -> 407.26153 | AF29: =if(AF$13=1,Actuals!AG64,'Key Assumptions'!AH35) -> 407.66879 | AG29: =if(AG$13=1,Actuals!AH64,'Key Assumptions'!AI35) -> 408.07646 | AH29: =if(AH$13=1,Actuals!AI64,'Key Assumptions'!AJ35) -> 408.48453 | AI29: =if(AI$13=1,Actuals!AJ64,'Key Assumptions'!AK35) -> 408.89302 | AJ29: =if(AJ$13=1,Actuals!AK64,'Key Assumptions'!AL35) -> 409.30191 | AK29: =if(AK$13=1,Actuals!AL64,'Key Assumptions'!AM35) -> 409.71121 | AL29: =if(AL$13=1,Actuals!AM64,'Key Assumptions'!AN35) -> 410.12093 | ... BT29: =if(BT$13=1,Actuals!BU64,'Key Assumptions'!BV35) -> 424.29759
B30: Total Operating Expenses | F30: $'000s | G30: =sum(G27:G29) -> 15000 | H30: =sum(H27:H29) -> 15155.27 | I30: =sum(I27:I29) -> 15448.956 | J30: =sum(J27:J29) -> 15635.366 | K30: =sum(K27:K29) -> 15824.026 | M30: =sum(M27:M29) -> 1250 | N30: =sum(N27:N29) -> 1250 | O30: =sum(O27:O29) -> 1250 | P30: =sum(P27:P29) -> 1250 | Q30: =sum(Q27:Q29) -> 1250 | R30: =sum(R27:R29) -> 1250 | S30: =sum(S27:S29) -> 1250 | T30: =sum(T27:T29) -> 1250 | ... BT30: =sum(BT27:BT29) -> 1325.93
B32: EBITDA | F32: $'000s | G32: =G23-G30 -> -2860.1731 | H32: =H23-H30 -> 1274.1352 | I32: =I23-I30 -> 5774.156 | J32: =J23-J30 -> 11001.895 | K32: =K23-K30 -> 16251.266 | M32: =M23-M30 -> -433.41333 | N32: =N23-N30 -> -403.90802 | O32: =O23-O30 -> -369.63761 | P32: =P23-P30 -> -343.62677 | Q32: =Q23-Q30 -> -321.37975 | R32: =R23-R30 -> -283.05715 | S32: =S23-S30 -> -236.76838 | T32: =T23-T30 -> -203.36049 | ... BT32: =BT23-BT30 -> 1554.7223
B33: EBITDA Margin | F33: % | G33: =G32/G19 -> -0.19332519 | H33: =H32/H19 -> 0.063465976 | I33: =I32/I19 -> 0.2176554 | J33: =J32/J19 -> 0.33042121 | K33: =K32/K19 -> 0.40532797 | M33: =M32/M19 -> -0.42460975 | N33: =N32/N19 -> -0.3819046 | O33: =O32/O19 -> -0.33589587 | P33: =P32/P19 -> -0.30329825 | Q33: =Q32/Q19 -> -0.27686646 | R33: =R32/R19 -> -0.23418729 | S33: =S32/S19 -> -0.18694117 | T33: =T32/T19 -> -0.1554388 | ... BT33: =BT32/BT19 -> 0.43176951

Sheet Customer Control
B2: Customer Control SaaS Financial Model
F5: =IF(F13=1,"Actual","Forecast") -> Actual | G5: =IF(G13=1,"Actual","Forecast") -> Actual | H5: =IF(H13=1,"Actual","Forecast") -> Forecast | I5: =IF(I13=1,"Actual","Forecast") -> Forecast | J5: =IF(J13=1,"Actual","Forecast") -> Forecast | L5: =IF(L13=1,"Actual","Forecast") -> Actual | M5: =IF(M13=1,"Actual","Forecast") -> Actual | N5: =IF(N13=1,"Actual","Forecast") -> Actual | O5: =IF(O13=1,"Actual","Forecast") -> Actual | P5: =IF(P13=1,"Actual","Forecast") -> Actual | Q5: =IF(Q13=1,"Actual","Forecast") -> Actual | R5: =IF(R13=1,"Actual","Forecast") -> Actual | S5: =IF(S13=1,"Actual","Forecast") -> Actual | ... BS5: =IF(BS13=1,"Actual","Forecast") -> Forecast
F6: =F7 -> 44562 | G6: =G7 -> 44927 | H6: =H7 -> 45292 | I6: =I7 -> 45658 | J6: =J7 -> 46023 | L6: =L7 -> 44562 | M6: =M7 -> 44593 | N6: =N7 -> 44621 | O6: =O7 -> 44652 | P6: =P7 -> 44682 | Q6: =Q7 -> 44713 | R6: =R7 -> 44743 | S6: =S7 -> 44774 | ... BS6: =BS7 -> 46357
E7: Start Date | F7: ='Key Assumptions'!D13 -> 44562 | G7: =F8+1 -> 44927 | H7: =G8+1 -> 45292 | I7: =H8+1 -> 45658 | J7: =I8+1 -> 46023 | L7: ='Key Assumptions'!D13 -> 44562 | M7: =L8+1 -> 44593 | N7: =M8+1 -> 44621 | O7: =N8+1 -> 44652 | P7: =O8+1 -> 44682 | Q7: =P8+1 -> 44713 | R7: =Q8+1 -> 44743 | S7: =R8+1 -> 44774 | T7: =S8+1 -> 44805 | ... BS7: =BR8+1 -> 46357
E8: End Date | F8: =EOMONTH(F7,11) -> 44926 | G8: =EOMONTH(G7,11) -> 45291 | H8: =EOMONTH(H7,11) -> 45657 | I8: =EOMONTH(I7,11) -> 46022 | J8: =EOMONTH(J7,11) -> 46387 | L8: =EOMONTH(L7,0) -> 44592 | M8: =EOMONTH(M7,0) -> 44620 | N8: =EOMONTH(N7,0) -> 44651 | O8: =EOMONTH(O7,0) -> 44681 | P8: =EOMONTH(P7,0) -> 44712 | Q8: =EOMONTH(Q7,0) -> 44742 | R8: =EOMONTH(R7,0) -> 44773 | S8: =EOMONTH(S7,0) -> 44804 | ... BS8: =EOMONTH(BS7,0) -> 46387
E9: Timeline | F9: =IF(F8-F7>35,"Annual","Monthly") -> Annual | G9: =IF(G8-G7>35,"Annual","Monthly") -> Annual | H9: =IF(H8-H7>35,"Annual","Monthly") -> Annual | I9: =IF(I8-I7>35,"Annual","Monthly") -> Annual | J9: =IF(J8-J7>35,"Annual","Monthly") -> Annual | L9: =IF(L8-L7>35,"Annual","Monthly") -> Monthly | M9: =IF(M8-M7>35,"Annual","Monthly") -> Monthly | N9: =IF(N8-N7>35,"Annual","Monthly") -> Monthly | O9: =IF(O8-O7>35,"Annual","Monthly") -> Monthly | P9: =IF(P8-P7>35,"Annual","Monthly") -> Monthly | Q9: =IF(Q8-Q7>35,"Annual","Monthly") -> Monthly | R9: =IF(R8-R7>35,"Annual","Monthly") -> Monthly | S9: =IF(S8-S7>35,"Annual","Monthly") -> Monthly | ... BS9: =IF(BS8-BS7>35,"Annual","Monthly") -> Monthly
E10: Year | F10: =YEAR(F7) -> 2022 | G10: =YEAR(G7) -> 2023 | H10: =YEAR(H7) -> 2024 | I10: =YEAR(I7) -> 2025 | J10: =YEAR(J7) -> 2026 | L10: =YEAR(L7) -> 2022 | M10: =YEAR(M7) -> 2022 | N10: =YEAR(N7) -> 2022 | O10: =YEAR(O7) -> 2022 | P10: =YEAR(P7) -> 2022 | Q10: =YEAR(Q7) -> 2022 | R10: =YEAR(R7) -> 2022 | S10: =YEAR(S7) -> 2022 | ... BS10: =YEAR(BS7) -> 2026
E12: Flag
E13: Historical Flag | F13: =IF(AND(F7>='Key Assumptions'!$D$13,F7<'Key Assumptions'!$D$14),1,0) -> 1 | G13: =IF(AND(G7>='Key Assumptions'!$D$13,G7<'Key Assumptions'!$D$14),1,0) -> 1 | H13: =IF(AND(H7>='Key Assumptions'!$D$13,H7<'Key Assumptions'!$D$14),1,0) -> 0 | I13: =IF(AND(I7>='Key Assumptions'!$D$13,I7<'Key Assumptions'!$D$14),1,0) -> 0 | J13: =IF(AND(J7>='Key Assumptions'!$D$13,J7<'Key Assumptions'!$D$14),1,0) -> 0 | L13: =IF(AND(L7>='Key Assumptions'!$D$13,L7<'Key Assumptions'!$D$14),1,0) -> 1 | M13: =IF(AND(M7>='Key Assumptions'!$D$13,M7<'Key Assumptions'!$D$14),1,0) -> 1 | N13: =IF(AND(N7>='Key Assumptions'!$D$13,N7<'Key Assumptions'!$D$14),1,0) -> 1 | O13: =IF(AND(O7>='Key Assumptions'!$D$13,O7<'Key Assumptions'!$D$14),1,0) -> 1 | P13: =IF(AND(P7>='Key Assumptions'!$D$13,P7<'Key Assumptions'!$D$14),1,0) -> 1 | Q13: =IF(AND(Q7>='Key Assumptions'!$D$13,Q7<'Key Assumptions'!$D$14),1,0) -> 1 | R13: =IF(AND(R7>='Key Assumptions'!$D$13,R7<'Key Assumptions'!$D$14),1,0) -> 1 | S13: =IF(AND(S7>='Key Assumptions'!$D$13,S7<'Key Assumptions'!$D$14),1,0) -> 1 | ... BS13: =IF(AND(BS7>='Key Assumptions'!$D$13,BS7<'Key Assumptions'!$D$14),1,0) -> 0
E14: Forecast Flag | F14: =IF(AND(F7>='Key Assumptions'!$D$15,F7<'Key Assumptions'!$D$16),1,0) -> 0 | G14: =IF(AND(G7>='Key Assumptions'!$D$15,G7<'Key Assumptions'!$D$16),1,0) -> 0 | H14: =IF(AND(H7>='Key Assumptions'!$D$15,H7<'Key Assumptions'!$D$16),1,0) -> 1 | I14: =IF(AND(I7>='Key Assumptions'!$D$15,I7<'Key Assumptions'!$D$16),1,0) -> 1 | J14: =IF(AND(J7>='Key Assumptions'!$D$15,J7<'Key Assumptions'!$D$16),1,0) -> 1 | L14: =IF(AND(L7>='Key Assumptions'!$D$15,L7<'Key Assumptions'!$D$16),1,0) -> 0 | M14: =IF(AND(M7>='Key Assumptions'!$D$15,M7<'Key Assumptions'!$D$16),1,0) -> 0 | N14: =IF(AND(N7>='Key Assumptions'!$D$15,N7<'Key Assumptions'!$D$16),1,0) -> 0 | O14: =IF(AND(O7>='Key Assumptions'!$D$15,O7<'Key Assumptions'!$D$16),1,0) -> 0 | P14: =IF(AND(P7>='Key Assumptions'!$D$15,P7<'Key Assumptions'!$D$16),1,0) -> 0 | Q14: =IF(AND(Q7>='Key Assumptions'!$D$15,Q7<'Key Assumptions'!$D$16),1,0) -> 0 | R14: =IF(AND(R7>='Key Assumptions'!$D$15,R7<'Key Assumptions'!$D$16),1,0) -> 0 | S14: =IF(AND(S7>='Key Assumptions'!$D$15,S7<'Key Assumptions'!$D$16),1,0) -> 0 | ... BS14: =IF(AND(BS7>='Key Assumptions'!$D$15,BS7<'Key Assumptions'!$D$16),1,0) -> 1
E15: Year Flag | F15: =COUNTA($F$7:F7) -> 1 | G15: =COUNTA($F$7:G7) -> 2 | H15: =COUNTA($F$7:H7) -> 3 | I15: =COUNTA($F$7:I7) -> 4 | J15: =COUNTA($F$7:J7) -> 5 | L15: =INDEX($F$15:$J$15,MATCH(YEAR(L$7),$F$10:$J$10,0)) -> 1 | M15: =INDEX($F$15:$J$15,MATCH(YEAR(M$7),$F$10:$J$10,0)) -> 1 | N15: =INDEX($F$15:$J$15,MATCH(YEAR(N$7),$F$10:$J$10,0)) -> 1 | O15: =INDEX($F$15:$J$15,MATCH(YEAR(O$7),$F$10:$J$10,0)) -> 1 | P15: =INDEX($F$15:$J$15,MATCH(YEAR(P$7),$F$10:$J$10,0)) -> 1 | Q15: =INDEX($F$15:$J$15,MATCH(YEAR(Q$7),$F$10:$J$10,0)) -> 1 | R15: =INDEX($F$15:$J$15,MATCH(YEAR(R$7),$F$10:$J$10,0)) -> 1 | S15: =INDEX($F$15:$J$15,MATCH(YEAR(S$7),$F$10:$J$10,0)) -> 1 | ... BS15: =INDEX($F$15:$J$15,MATCH(YEAR(BS$7),$F$10:$J$10,0)) -> 5
B17: Customer Summary
B18: Beginning Customers | E18: # | F18: {=INDEX($L18:$BS18,MATCH(F$7,L$7:BG$7,0))} -> 500 | G18: =INDEX($L18:$BG18,MATCH(G$7,M$7:BT$7,0)) -> 638 | H18: =INDEX($L18:$BG18,MATCH(H$7,N$7:BU$7,0)) -> 766.13997 | I18: =INDEX($L18:$BG18,MATCH(I$7,O$7:BV$7,0)) -> 912.91999 | J18: =INDEX($L18:$BG18,MATCH(J$7,P$7:BW$7,0)) -> 1062.0217 | L18: =IF(L$13=1,Actuals!N29,K21) -> 500 | M18: =IF(M$13=1,Actuals!O29,L21) -> 509 | N18: =IF(N$13=1,Actuals!P29,M21) -> 519 | O18: =IF(O$13=1,Actuals!Q29,N21) -> 531 | P18: =IF(P$13=1,Actuals!R29,O21) -> 543 | Q18: =IF(Q$13=1,Actuals!S29,P21) -> 556 | R18: =IF(R$13=1,Actuals!T29,Q21) -> 576 | S18: =IF(S$13=1,Actuals!U29,R21) -> 595 | ... BH18: =IF(BH$13=1,Actuals!BJ29,BG21) -> 1116.221 | BI18: =IF(BI$13=1,Actuals!BW29,BH21) -> 1129.7593 | BJ18: =IF(BJ$13=1,Actuals!BX29,BI21) -> 1143.3059 | BK18: =IF(BK$13=1,Actuals!BY29,BJ21) -> 1156.8576 | BL18: =IF(BL$13=1,Actuals!BZ29,BK21) -> 1170.4166 | BM18: =IF(BM$13=1,Actuals!CA29,BL21) -> 1183.9761 | BN18: =IF(BN$13=1,Actuals!CB29,BM21) -> 1197.5296 | BO18: =IF(BO$13=1,Actuals!CC29,BN21) -> 1211.0771 | BP18: =IF(BP$13=1,Actuals!CD29,BO21) -> 1224.6219 | ... BS18: =IF(BS$13=1,Actuals!CG29,BR21) -> 1265.262
B19: New Customers | E19: # | F19: =SUMIFS($L19:$BS19,$L$15:$BS$15,F$15) -> 248 | G19: =SUMIFS($L19:$BS19,$L$15:$BS$15,G$15) -> 240 | H19: =SUMIFS($L19:$BS19,$L$15:$BS$15,H$15) -> 228 | I19: =SUMIFS($L19:$BS19,$L$15:$BS$15,I$15) -> 228 | J19: =SUMIFS($L19:$BS19,$L$15:$BS$15,J$15) -> 228 | L19: =IF(L$13=1,Actuals!N30,L29) -> 16 | M19: =IF(M$13=1,Actuals!O30,M29) -> 21 | N19: =IF(N$13=1,Actuals!P30,N29) -> 23 | O19: =IF(O$13=1,Actuals!Q30,O29) -> 19 | P19: =IF(P$13=1,Actuals!R30,P29) -> 18 | Q19: =IF(Q$13=1,Actuals!S30,Q29) -> 28 | R19: =IF(R$13=1,Actuals!T30,R29) -> 25 | S19: =IF(S$13=1,Actuals!U30,S29) -> 23 | ... BH19: =IF(BH$13=1,Actuals!BJ30,BH29) -> 19 | BI19: =IF(BI$13=1,Actuals!BW30,BI29) -> 19 | BJ19: =IF(BJ$13=1,Actuals!BX30,BJ29) -> 19 | BK19: =IF(BK$13=1,Actuals!BY30,BK29) -> 19 | BL19: =IF(BL$13=1,Actuals!BZ30,BL29) -> 19 | BM19: =IF(BM$13=1,Actuals!CA30,BM29) -> 19 | BN19: =IF(BN$13=1,Actuals!CB30,BN29) -> 19 | BO19: =IF(BO$13=1,Actuals!CC30,BO29) -> 19 | BP19: =IF(BP$13=1,Actuals!CD30,BP29) -> 19 | ... BS19: =IF(BS$13=1,Actuals!CG30,BS29) -> 19
B20: Churned Customers | E20: # | F20: =SUMIFS($L20:$BS20,$L$15:$BS$15,F$15) -> -100 | G20: =SUMIFS($L20:$BS20,$L$15:$BS$15,G$15) -> -93.354255 | H20: =SUMIFS($L20:$BS20,$L$15:$BS$15,H$15) -> -69.022628 | I20: =SUMIFS($L20:$BS20,$L$15:$BS$15,I$15) -> -65.40207 | J20: =SUMIFS($L20:$BS20,$L$15:$BS$15,J$15) -> -65.404935 | L20: =IF(L$13=1,Actuals!N31,-L37*L38) -> -7 | M20: =IF(M$13=1,Actuals!O31,-M37*M38) -> -11 | N20: =IF(N$13=1,Actuals!P31,-N37*N38) -> -11 | O20: =IF(O$13=1,Actuals!Q31,-O37*O38) -> -7 | P20: =IF(P$13=1,Actuals!R31,-P37*P38) -> -5 | Q20: =IF(Q$13=1,Actuals!S31,-Q37*Q38) -> -8 | R20: =IF(R$13=1,Actuals!T31,-R37*R38) -> -6 | S20: =IF(S$13=1,Actuals!U31,-S37*S38) -> -12 | ... BS20: =IF(BS$13=1,Actuals!BU31,-BS37*BS38) -> -5.4459327
B21: Ending Customers | E21: # | F21: =INDEX($L21:$BS21,MATCH(F$8,L$8:BS$8,0)) -> 648 | G21: =INDEX($L21:$BS21,MATCH(G$8,M$8:BT$8,0)) -> 780.14179 | H21: =INDEX($L21:$BS21,MATCH(H$8,N$8:BU$8,0)) -> 926.48655 | I21: =INDEX($L21:$BS21,MATCH(I$8,O$8:BV$8,0)) -> 1075.5822 | J21: =INDEX($L21:$BS21,MATCH(J$8,P$8:BW$8,0)) -> 1224.6219 | L21: =IF(L$13=1,Actuals!N32,SUM(L18:L20)) -> 509 | M21: =IF(M$13=1,Actuals!O32,SUM(M18:M20)) -> 519 | N21: =IF(N$13=1,Actuals!P32,SUM(N18:N20)) -> 531 | O21: =IF(O$13=1,Actuals!Q32,SUM(O18:O20)) -> 543 | P21: =IF(P$13=1,Actuals!R32,SUM(P18:P20)) -> 556 | Q21: =IF(Q$13=1,Actuals!S32,SUM(Q18:Q20)) -> 576 | R21: =IF(R$13=1,Actuals!T32,SUM(R18:R20)) -> 595 | S21: =IF(S$13=1,Actuals!U32,SUM(S18:S20)) -> 606 | ... BH21: =IF(BH$13=1,Actuals!BJ32,SUM(BH18:BH20)) -> 1129.7593 | BI21: =IF(BI$13=1,Actuals!BW32,SUM(BI18:BI20)) -> 1143.3059 | BJ21: =IF(BJ$13=1,Actuals!BX32,SUM(BJ18:BJ20)) -> 1156.8576 | BK21: =IF(BK$13=1,Actuals!BY32,SUM(BK18:BK20)) -> 1170.4166 | BL21: =IF(BL$13=1,Actuals!BZ32,SUM(BL18:BL20)) -> 1183.9761 | BM21: =IF(BM$13=1,Actuals!CA32,SUM(BM18:BM20)) -> 1197.5296 | BN21: =IF(BN$13=1,Actuals!CB32,SUM(BN18:BN20)) -> 1211.0771 | BO21: =IF(BO$13=1,Actuals!CC32,SUM(BO18:BO20)) -> 1224.6219 | BP21: =IF(BP$13=1,Actuals!CD32,SUM(BP18:BP20)) -> 1238.165 | ... BS21: =IF(BS$13=1,Actuals!CG32,SUM(BS18:BS20)) -> 1278.8161
B23: Net new customers | E23: # | F23: =F19+F20 -> 148 | G23: =G19+G20 -> 146.64575 | H23: =H19+H20 -> 158.97737 | I23: =I19+I20 -> 162.59793 | J23: =J19+J20 -> 162.59507 | L23: =L19+L20 -> 9 | M23: =M19+M20 -> 10 | N23: =N19+N20 -> 12 | O23: =O19+O20 -> 12 | P23: =P19+P20 -> 13 | Q23: =Q19+Q20 -> 20 | R23: =R19+R20 -> 19 | S23: =S19+S20 -> 11 | ... BS23: =BS19+BS20 -> 13.554067
B25: New Customers Calculation
B26: Pipeline Leads | E26: # | F26: =SUMIFS($L26:$BS26,$L$15:$BS$15,F$15) -> 6108 | G26: =SUMIFS($L26:$BS26,$L$15:$BS$15,G$15) -> 5986 | H26: =SUMIFS($L26:$BS26,$L$15:$BS$15,H$15) -> 6000 | I26: =SUMIFS($L26:$BS26,$L$15:$BS$15,I$15) -> 6000 | J26: =SUMIFS($L26:$BS26,$L$15:$BS$15,J$15) -> 6000 | L26: =IF(L$13=1,Actuals!N38,'Key Assumptions'!O26) -> 466 | M26: =IF(M$13=1,Actuals!O38,'Key Assumptions'!P26) -> 534 | N26: =IF(N$13=1,Actuals!P38,'Key Assumptions'!Q26) -> 485 | O26: =IF(O$13=1,Actuals!Q38,'Key Assumptions'!R26) -> 507 | P26: =IF(P$13=1,Actuals!R38,'Key Assumptions'!S26) -> 515 | Q26: =IF(Q$13=1,Actuals!S38,'Key Assumptions'!T26) -> 542 | R26: =IF(R$13=1,Actuals!T38,'Key Assumptions'!U26) -> 466 | S26: =IF(S$13=1,Actuals!U38,'Key Assumptions'!V26) -> 541 | ... BS26: =IF(BS$13=1,Actuals!BU38,'Key Assumptions'!BV26) -> 500
B27: MQL | E27: # | F27: =SUMIFS($L27:$BS27,$L$15:$BS$15,F$15) -> 787 | G27: =SUMIFS($L27:$BS27,$L$15:$BS$15,G$15) -> 695 | H27: =SUMIFS($L27:$BS27,$L$15:$BS$15,H$15) -> 600 | I27: =SUMIFS($L27:$BS27,$L$15:$BS$15,I$15) -> 600 | J27: =SUMIFS($L27:$BS27,$L$15:$BS$15,J$15) -> 600 | L27: =if(L13=1,Actuals!N39,round(L26*L31,0)) -> 61 | M27: =if(M13=1,Actuals!O39,round(M26*M31,0)) -> 80 | N27: =if(N13=1,Actuals!P39,round(N26*N31,0)) -> 68 | O27: =if(O13=1,Actuals!Q39,round(O26*O31,0)) -> 61 | P27: =if(P13=1,Actuals!R39,round(P26*P31,0)) -> 62 | Q27: =if(Q13=1,Actuals!S39,round(Q26*Q31,0)) -> 76 | R27: =if(R13=1,Actuals!T39,round(R26*R31,0)) -> 70 | S27: =if(S13=1,Actuals!U39,round(S26*S31,0)) -> 70 | ... BS27: =if(BS13=1,Actuals!BU39,round(BS26*BS31,0)) -> 50
B28: SQL | E28: # | F28: =SUMIFS($L28:$BS28,$L$15:$BS$15,F$15) -> 353 | G28: =SUMIFS($L28:$BS28,$L$15:$BS$15,G$15) -> 329 | H28: =SUMIFS($L28:$BS28,$L$15:$BS$15,H$15) -> 300 | I28: =SUMIFS($L28:$BS28,$L$15:$BS$15,I$15) -> 300 | J28: =SUMIFS($L28:$BS28,$L$15:$BS$15,J$15) -> 300 | L28: =if(L13=1,Actuals!N40,round(L27*L32,0)) -> 22 | M28: =if(M13=1,Actuals!O40,round(M27*M32,0)) -> 31 | N28: =if(N13=1,Actuals!P40,round(N27*N32,0)) -> 31 | O28: =if(O13=1,Actuals!Q40,round(O27*O32,0)) -> 28 | P28: =if(P13=1,Actuals!R40,round(P27*P32,0)) -> 24 | Q28: =if(Q13=1,Actuals!S40,round(Q27*Q32,0)) -> 41 | R28: =if(R13=1,Actuals!T40,round(R27*R32,0)) -> 37 | S28: =if(S13=1,Actuals!U40,round(S27*S32,0)) -> 33 | ... BS28: =if(BS13=1,Actuals!BU40,round(BS27*BS32,0)) -> 25
B29: Deals / New Customers | E29: # | F29: =SUMIFS($L29:$BS29,$L$15:$BS$15,F$15) -> 248 | G29: =SUMIFS($L29:$BS29,$L$15:$BS$15,G$15) -> 240 | H29: =SUMIFS($L29:$BS29,$L$15:$BS$15,H$15) -> 228 | I29: =SUMIFS($L29:$BS29,$L$15:$BS$15,I$15) -> 228 | J29: =SUMIFS($L29:$BS29,$L$15:$BS$15,J$15) -> 228 | L29: =if(L13=1,Actuals!N41,round(L28*L33,0)) -> 16 | M29: =if(M13=1,Actuals!O41,round(M28*M33,0)) -> 21 | N29: =if(N13=1,Actuals!P41,round(N28*N33,0)) -> 23 | O29: =if(O13=1,Actuals!Q41,round(O28*O33,0)) -> 19 | P29: =if(P13=1,Actuals!R41,round(P28*P33,0)) -> 18 | Q29: =if(Q13=1,Actuals!S41,round(Q28*Q33,0)) -> 28 | R29: =if(R13=1,Actuals!T41,round(R28*R33,0)) -> 25 | S29: =if(S13=1,Actuals!U41,round(S28*S33,0)) -> 23 | ... BS29: =if(BS13=1,Actuals!BU41,round(BS28*BS33,0)) -> 19
B31: Pipeline to MQL (conversion rate) | E31: % | F31: =AVERAGEIFS($L31:$BS31,$L$15:$BS$15,F$15) -> 0.1 | G31: =AVERAGEIFS($L31:$BS31,$L$15:$BS$15,G$15) -> 0.1 | H31: =AVERAGEIFS($L31:$BS31,$L$15:$BS$15,H$15) -> 0.1 | I31: =AVERAGEIFS($L31:$BS31,$L$15:$BS$15,I$15) -> 0.1 | J31: =AVERAGEIFS($L31:$BS31,$L$15:$BS$15,J$15) -> 0.1 | L31: 0.1 | M31: 0.1 | N31: 0.1 | O31: 0.1 | P31: 0.1 | Q31: 0.1 | R31: 0.1 | S31: 0.1 | T31: 0.1 | U31: 0.1 | V31: 0.1 | W31: 0.1 | X31: 0.1 | Y31: 0.1 | Z31: 0.1 | AA31: 0.1 | AB31: 0.1 | AC31: 0.1 | AD31: 0.1 | AE31: 0.1 | AF31: 0.1 | AG31: 0.1 | AH31: 0.1 | AI31: 0.1 | AJ31: 0.1 | AK31: 0.1 | AL31: 0.1 | AM31: 0.1 | AN31: 0.1 | AO31: 0.1 | AP31: 0.1 | AQ31: 0.1 | AR31: 0.1 | AS31: 0.1 | AT31: 0.1 | AU31: 0.1 | AV31: 0.1 | AW31: 0.1 | AX31: 0.1 | AY31: 0.1 | AZ31: 0.1 | BA31: 0.1 | BB31: 0.1 | BC31: 0.1 | BD31: 0.1 | BE31: 0.1 | BF31: 0.1 | BG31: 0.1 | BH31: 0.1 | BI31: 0.1 | BJ31: 0.1 | BK31: 0.1 | BL31: 0.1 | BM31: 0.1 | BN31: 0.1 | BO31: 0.1 | BP31: 0.1 | BQ31: 0.1 | BR31: 0.1 | BS31: 0.1
B32: MQL to SQL (conversion rate) | E32: % | F32: =AVERAGEIFS($L32:$BS32,$L$15:$BS$15,F$15) -> 0.5 | G32: =AVERAGEIFS($L32:$BS32,$L$15:$BS$15,G$15) -> 0.5 | H32: =AVERAGEIFS($L32:$BS32,$L$15:$BS$15,H$15) -> 0.5 | I32: =AVERAGEIFS($L32:$BS32,$L$15:$BS$15,I$15) -> 0.5 | J32: =AVERAGEIFS($L32:$BS32,$L$15:$BS$15,J$15) -> 0.5 | L32: 0.5 | M32: 0.5 | N32: 0.5 | O32: 0.5 | P32: 0.5 | Q32: 0.5 | R32: 0.5 | S32: 0.5 | T32: 0.5 | U32: 0.5 | V32: 0.5 | W32: 0.5 | X32: 0.5 | Y32: 0.5 | Z32: 0.5 | AA32: 0.5 | AB32: 0.5 | AC32: 0.5 | AD32: 0.5 | AE32: 0.5 | AF32: 0.5 | AG32: 0.5 | AH32: 0.5 | AI32: 0.5 | AJ32: 0.5 | AK32: 0.5 | AL32: 0.5 | AM32: 0.5 | AN32: 0.5 | AO32: 0.5 | AP32: 0.5 | AQ32: 0.5 | AR32: 0.5 | AS32: 0.5 | AT32: 0.5 | AU32: 0.5 | AV32: 0.5 | AW32: 0.5 | AX32: 0.5 | AY32: 0.5 | AZ32: 0.5 | BA32: 0.5 | BB32: 0.5 | BC32: 0.5 | BD32: 0.5 | BE32: 0.5 | BF32: 0.5 | BG32: 0.5 | BH32: 0.5 | BI32: 0.5 | BJ32: 0.5 | BK32: 0.5 | BL32: 0.5 | BM32: 0.5 | BN32: 0.5 | BO32: 0.5 | BP32: 0.5 | BQ32: 0.5 | BR32: 0.5 | BS32: 0.5
B33: SQL to Deals (conversion rate) | E33: % | F33: =AVERAGEIFS($L33:$BS33,$L$15:$BS$15,F$15) -> 0.75 | G33: =AVERAGEIFS($L33:$BS33,$L$15:$BS$15,G$15) -> 0.75 | H33: =AVERAGEIFS($L33:$BS33,$L$15:$BS$15,H$15) -> 0.75 | I33: =AVERAGEIFS($L33:$BS33,$L$15:$BS$15,I$15) -> 0.75 | J33: =AVERAGEIFS($L33:$BS33,$L$15:$BS$15,J$15) -> 0.75 | L33: 0.75 | M33: 0.75 | N33: 0.75 | O33: 0.75 | P33: 0.75 | Q33: 0.75 | R33: 0.75 | S33: 0.75 | T33: 0.75 | U33: 0.75 | V33: 0.75 | W33: 0.75 | X33: 0.75 | Y33: 0.75 | Z33: 0.75 | AA33: 0.75 | AB33: 0.75 | AC33: 0.75 | AD33: 0.75 | AE33: 0.75 | AF33: 0.75 | AG33: 0.75 | AH33: 0.75 | AI33: 0.75 | AJ33: 0.75 | AK33: 0.75 | AL33: 0.75 | AM33: 0.75 | AN33: 0.75 | AO33: 0.75 | AP33: 0.75 | AQ33: 0.75 | AR33: 0.75 | AS33: 0.75 | AT33: 0.75 | AU33: 0.75 | AV33: 0.75 | AW33: 0.75 | AX33: 0.75 | AY33: 0.75 | AZ33: 0.75 | BA33: 0.75 | BB33: 0.75 | BC33: 0.75 | BD33: 0.75 | BE33: 0.75 | BF33: 0.75 | BG33: 0.75 | BH33: 0.75 | BI33: 0.75 | BJ33: 0.75 | BK33: 0.75 | BL33: 0.75 | BM33: 0.75 | BN33: 0.75 | BO33: 0.75 | BP33: 0.75 | BQ33: 0.75 | BR33: 0.75 | BS33: 0.75
B36: Churned Customers Calculation
B37: =Summary!B36 -> Customers Available to Renew | E37: # | F37: =Summary!G36 -> 395 | G37: =Summary!H36 -> 324 | H37: =Summary!I36 -> 240 | I37: =Summary!J36 -> 228 | J37: =Summary!K36 -> 228 | L37: =if(L13=1,Actuals!N71,A19) -> 32 | M37: =if(M13=1,Actuals!O71,B19) -> 41 | N37: =if(N13=1,Actuals!P71,C19) -> 42 | O37: =if(O13=1,Actuals!Q71,#REF!) -> 27 | P37: =if(P13=1,Actuals!R71,D19) -> 35 | Q37: =if(Q13=1,Actuals!S71,E19) -> 34 | R37: =if(R13=1,Actuals!T71,F19) -> 39 | S37: =if(S13=1,Actuals!U71,G19) -> 33 | T37: =if(T13=1,Actuals!V71,H19) -> 30 | U37: =if(U13=1,Actuals!W71,I19) -> 30 | V37: =if(V13=1,Actuals!X71,J19) -> 27 | W37: =if(W13=1,Actuals!Y71,K19) -> 25 | ... BS37: =if(BS13=1,Actuals!BU71,BG19) -> 19
B38: =Summary!B38 -> % Customer Churn | E38: % | F38: =Summary!G38 -> 0.25612251 | G38: =Summary!H38 -> 0.28838415 | H38: =Summary!I38 -> 0.28724948 | I38: =Summary!J38 -> 0.28685119 | J38: =Summary!K38 -> 0.28686375 | L38: =if(L13=1,-L20/L37,AVERAGE(C38:F38)) -> 0.21875 | M38: =if(M13=1,-M20/M37,AVERAGE(D38:G38)) -> 0.26829268 | N38: =if(N13=1,-N20/N37,AVERAGE(D38:H38)) -> 0.26190476 | O38: =if(O13=1,-O20/O37,AVERAGE(E38:I38)) -> 0.25925926 | P38: =if(P13=1,-P20/P37,AVERAGE(F38:J38)) -> 0.14285714 | Q38: =if(Q13=1,-Q20/Q37,AVERAGE(G38:K38)) -> 0.23529412 | R38: =if(R13=1,-R20/R37,AVERAGE(H38:L38)) -> 0.15384615 | S38: =if(S13=1,-S20/S37,AVERAGE(I38:M38)) -> 0.36363636 | T38: =if(T13=1,-T20/T37,AVERAGE(J38:N38)) -> 0.33333333 | U38: =if(U13=1,-U20/U37,AVERAGE(K38:O38)) -> 0.3 | ... BS38: =if(BS13=1,-BS20/BS37,AVERAGE(BI38:BM38)) -> 0.28662804

Sheet Dashboard
B4: P&L | D4: ="FY"&right('P&L'!G10,2) -> FY22 | E4: ="FY"&right('P&L'!H10,2) -> FY23 | F4: ="FY"&right('P&L'!I10,2) -> FY24 | G4: ="FY"&right('P&L'!J10,2) -> FY25 | H4: ="FY"&right('P&L'!K10,2) -> FY26
B5: ='P&L'!B19 -> Revenue | C5: ='P&L'!C19 | D5: ='P&L'!G19 -> 14794.622 | E5: ='P&L'!H19 -> 20075.879 | F5: ='P&L'!I19 -> 26528.89 | G5: ='P&L'!J19 -> 33296.577 | H5: ='P&L'!K19 -> 40094.115
B6: ='P&L'!B22 -> COGS | C6: ='P&L'!C22 | D6: ='P&L'!G22 -> -2654.7948 | E6: ='P&L'!H22 -> -3646.4742 | F6: ='P&L'!I22 -> -5305.7779 | G6: ='P&L'!J22 -> -6659.3154 | H6: ='P&L'!K22 -> -8018.8231
B7: ='P&L'!B23 -> Gross Profit | C7: ='P&L'!C23 | D7: ='P&L'!G23 -> 12139.827 | E7: ='P&L'!H23 -> 16429.405 | F7: ='P&L'!I23 -> 21223.112 | G7: ='P&L'!J23 -> 26637.262 | H7: ='P&L'!K23 -> 32075.292
B9: ='P&L'!B27 -> G&A | D9: =-'P&L'!G27 -> -3000 | E9: =-'P&L'!H27 -> -3031.0539 | F9: =-'P&L'!I27 -> -3089.7912 | G9: =-'P&L'!J27 -> -3127.0733 | H9: =-'P&L'!K27 -> -3164.8052
B10: ='P&L'!B28 -> S&M | D10: =-'P&L'!G28 -> -7200 | E10: =-'P&L'!H28 -> -7274.5294 | F10: =-'P&L'!I28 -> -7415.4988 | G10: =-'P&L'!J28 -> -7504.9758 | H10: =-'P&L'!K28 -> -7595.5325
B11: ='P&L'!B29 -> R&D | D11: =-'P&L'!G29 -> -4800 | E11: =-'P&L'!H29 -> -4849.6862 | F11: =-'P&L'!I29 -> -4943.6658 | G11: =-'P&L'!J29 -> -5003.3172 | H11: =-'P&L'!K29 -> -5063.6883
B12: ='P&L'!B30 -> Total Operating Expenses | D12: ='P&L'!G30 -> 15000 | E12: ='P&L'!H30 -> 15155.27 | F12: ='P&L'!I30 -> 15448.956 | G12: ='P&L'!J30 -> 15635.366 | H12: ='P&L'!K30 -> 15824.026
B14: ='P&L'!B32 -> EBITDA | D14: ='P&L'!G32 -> -2860.1731 | E14: ='P&L'!H32 -> 1274.1352 | F14: ='P&L'!I32 -> 5774.156 | G14: ='P&L'!J32 -> 11001.895 | H14: ='P&L'!K32 -> 16251.266
B15: ='P&L'!B33 -> EBITDA Margin | D15: ='P&L'!G33 -> -0.19332519 | E15: ='P&L'!H33 -> 0.063465976 | F15: ='P&L'!I33 -> 0.2176554 | G15: ='P&L'!J33 -> 0.33042121 | H15: ='P&L'!K33 -> 0.40532797
A43: Chart Data
B44: ARR Waterfall
B45: Beginning ARR | C45: =Summary!G18/1000 -> 11935
B46: =Summary!B19 -> New ARR | C46: =sum(Summary!G19:K19)/1000 -> 29774.236
B47: =Summary!B20 -> Expansion | C47: =sum(Summary!G20:K20)/1000 -> 11705.913
B48: =Summary!B21 -> Churn ARR | C48: =sum(Summary!G21:K21)/1000 -> -10205.365
B49: =Summary!B23
C50: =D4 -> FY22 | D50: =E4 -> FY23 | E50: =F4 -> FY24 | F50: =G4 -> FY25 | G50: =H4 -> FY26
B51: Customer Retention | C51: =Summary!G41 -> 0.74683544 | D51: =Summary!H41 -> 0.71186958 | E51: =Summary!I41 -> 0.71240572 | F51: =Summary!J41 -> 0.71314881 | G51: =Summary!K41 -> 0.71313625
B52: Gross Dollar Retention | C52: =Summary!G42 -> 0.7366 | D52: =Summary!H42 -> 0.7465 | E52: =Summary!I42 -> 0.8729 | F52: =Summary!J42 -> 0.89 | G52: =Summary!K42 -> 0.9
B53: Net Dollar Retention | C53: =Summary!G43 -> 1.5208282 | D53: =Summary!H43 -> 1.7663209 | E53: =Summary!I43 -> 1.2 | F53: =Summary!J43 -> 1.15 | G53: =Summary!K43 -> 1.21
C55: =C50 -> FY22 | D55: =D50 -> FY23 | E55: =E50 -> FY24 | F55: =F50 -> FY25 | G55: =G50 -> FY26
B56: =Summary!B47 -> LTV | C56: =Summary!G47 -> 1021595.8 | D56: =Summary!H47 -> 1010950.2 | E56: =Summary!I47 -> 1140714.3 | F56: =Summary!J47 -> 1145057.5 | G56: =Summary!K47 -> 1144996.7
B57: =Summary!B48 -> CAC | C57: =Summary!G48 -> 359046.22 | D57: =Summary!H48 -> 369780.86 | E57: =Summary!I48 -> 382869.97 | F57: =Summary!J48 -> 390289.41 | G57: =Summary!K48 -> 394998.73
B58: =Summary!B49 -> LTV:CAC | C58: =Summary!G49 -> 2.8453044 | D58: =Summary!H49 -> 2.7339169 | E58: =Summary!I49 -> 2.9793779 | F58: =Summary!J49 -> 2.9338677 | G58: =Summary!K49 -> 2.8987353
